[{"Subscription Type": "Subscriber", "End Date": "1/5/2014 1:22", "Bike #": "318", "Zip Code": "94102", "Start Terminal": "60", "End Station": "Civic Center BART (7th at Market)", "Start Station": "Embarcadero at Sansome", "Duration": "926", "Start Date": "1/5/2014 1:06", "Trip ID": "142758", "End Terminal": "72"}, {"Subscription Type": "Subscriber", "End Date": "1/5/2014 1:10", "Bike #": "526", "Zip Code": "94107", "Start Terminal": "47", "End Station": "Howard at 2nd", "Start Station": "Post at Kearney", "Duration": "148", "Start Date": "1/5/2014 1:08", "Trip ID": "142759", "End Terminal": "63"}, {"Subscription Type": "Subscriber", "End Date": "1/5/2014 1:41", "Bike #": "44", "Zip Code": "95126", "Start Terminal": "4", "End Station": "San Jose Diridon Caltrain Station", "Start Station": "Santa Clara at Almaden", "Duration": "232", "Start Date": "1/5/2014 1:38", "Trip ID": "142760", "End Terminal": "2"}, {"Subscription Type": "Subscriber", "End Date": "1/5/2014 1:48", "Bike #": "675", "Zip Code": "95112", "Start Terminal": "2", "End Station": "Japantown", "Start Station": "San Jose Diridon Caltrain Station", "Duration": "639", "Start Date": "1/5/2014 1:37", "Trip ID": "142761", "End Terminal": "9"}, {"Subscription Type": "Subscriber", "End Date": "1/5/2014 2:23", "Bike #": "415", "Zip Code": "94111", "Start Terminal": "63", "End Station": "Howard at 2nd", "Start Station": "Howard at 2nd", "Duration": "280", "Start Date": "1/5/2014 2:18", "Trip ID": "142762", "End Terminal": "63"}, {"Subscription Type": "Customer", "End Date": "1/5/2014 5:01", "Bike #": "347", "Zip Code": "94111", "Start Terminal": "42", "End Station": "Davis at Jackson", "Start Station": "Davis at Jackson", "Duration": "7818", "Start Date": "1/5/2014 2:51", "Trip ID": "142763", "End Terminal": "42"}, {"Subscription Type": "Customer", "End Date": "1/5/2014 5:02", "Bike #": "380", "Zip Code": "94111", "Start Terminal": "42", "End Station": "Davis at Jackson", "Start Station": "Davis at Jackson", "Duration": "7593", "Start Date": "1/5/2014 2:55", "Trip ID": "142764", "End Terminal": "42"}, {"Subscription Type": "Customer", "End Date": "1/5/2014 5:02", "Bike #": "352", "Zip Code": "94111", "Start Terminal": "42", "End Station": "Davis at Jackson", "Start Station": "Davis at Jackson", "Duration": "7566", "Start Date": "1/5/2014 2:56", "Trip ID": "142765", "End Terminal": "42"}, {"Subscription Type": "Subscriber", "End Date": "1/5/2014 6:52", "Bike #": "363", "Zip Code": "94103", "Start Terminal": "57", "End Station": "2nd at Folsom", "Start Station": "5th at Howard", "Duration": "327", "Start Date": "1/5/2014 6:47", "Trip ID": "142767", "End Terminal": "62"}, {"Subscription Type": "Subscriber", "End Date": "1/5/2014 7:18", "Bike #": "548", "Zip Code": "94103", "Start Terminal": "77", "End Station": "Steuart at Market", "Start Station": "Market at Sansome", "Duration": "278", "Start Date": "1/5/2014 7:13", "Trip ID": "142784", "End Terminal": "74"}, {"Subscription Type": "Customer", "End Date": "1/5/2014 7:53", "Bike #": "319", "Zip Code": "19355", "Start Terminal": "57", "End Station": "San Francisco Caltrain 2 (330 Townsend)", "Start Station": "5th at Howard", "Duration": "444", "Start Date": "1/5/2014 7:46", "Trip ID": "142785", "End Terminal": "69"}, {"Subscription Type": "Customer", "End Date": "1/5/2014 9:07", "Bike #": "274", "Zip Code": "94112", "Start Terminal": "50", "End Station": "Harry Bridges Plaza (Ferry Building)", "Start Station": "Harry Bridges Plaza (Ferry Building)", "Duration": "4668", "Start Date": "1/5/2014 7:49", "Trip ID": "142786", "End Terminal": "50"}, {"Subscription Type": "Customer", "End Date": "1/5/2014 14:10", "Bike #": "540", "Zip Code": "7029", "Start Terminal": "77", "End Station": "Market at 4th", "Start Station": "Market at Sansome", "Duration": "22448", "Start Date": "1/5/2014 7:56", "Trip ID": "142787", "End Terminal": "76"}, {"Subscription Type": "Subscriber", "End Date": "1/5/2014 8:11", "Bike #": "463", "Zip Code": "94102", "Start Terminal": "41", "End Station": "Powell Street BART", "Start Station": "Clay at Battery", "Duration": "429", "Start Date": "1/5/2014 8:04", "Trip ID": "142788", "End Terminal": "53"}, {"Subscription Type": "Subscriber", "End Date": "1/5/2014 8:16", "Bike #": "277", "Zip Code": "94133", "Start Terminal": "60", "End Station": "Temporary Transbay Terminal (Howard at Beale)", "Start Station": "Embarcadero at Sansome", "Duration": "449", "Start Date": "1/5/2014 8:09", "Trip ID": "142789", "End Terminal": "55"}, {"Subscription Type": "Subscriber", "End Date": "1/5/2014 8:34", "Bike #": "672", "Zip Code": "95122", "Start Terminal": "9", "End Station": "Japantown", "Start Station": "Japantown", "Duration": "482", "Start Date": "1/5/2014 8:26", "Trip ID": "142790", "End Terminal": "9"}, {"Subscription Type": "Subscriber", "End Date": "1/5/2014 8:42", "Bike #": "489", "Zip Code": "94102", "Start Terminal": "53", "End Station": "South Van Ness at Market", "Start Station": "Powell Street BART", "Duration": "389", "Start Date": "1/5/2014 8:35", "Trip ID": "142791", "End Terminal": "66"}, {"Subscription Type": "Subscriber", "End Date": "1/5/2014 8:47", "Bike #": "546", "Zip Code": "94133", "Start Terminal": "60", "End Station": "Yerba Buena Center of the Arts (3rd @ Howard)", "Start Station": "Embarcadero at Sansome", "Duration": "652", "Start Date": "1/5/2014 8:36", "Trip ID": "142792", "End Terminal": "68"}, {"Subscription Type": "Customer", "End Date": "1/5/2014 9:15", "Bike #": "503", "Zip Code": "93924", "Start Terminal": "71", "End Station": "Grant Avenue at Columbus Avenue", "Start Station": "Powell at Post (Union Square)", "Duration": "1954", "Start Date": "1/5/2014 8:43", "Trip ID": "142793", "End Terminal": "73"}, {"Subscription Type": "Subscriber", "End Date": "1/5/2014 9:08", "Bike #": "433", "Zip Code": "95815", "Start Terminal": "76", "End Station": "Beale at Market", "Start Station": "Market at 4th", "Duration": "330", "Start Date": "1/5/2014 9:02", "Trip ID": "142794", "End Terminal": "56"}, {"Subscription Type": "Subscriber", "End Date": "1/5/2014 9:09", "Bike #": "510", "Zip Code": "94105", "Start Terminal": "54", "End Station": "San Francisco Caltrain (Townsend at 4th)", "Start Station": "Embarcadero at Bryant", "Duration": "353", "Start Date": "1/5/2014 9:03", "Trip ID": "142795", "End Terminal": "70"}, {"Subscription Type": "Subscriber", "End Date": "1/5/2014 9:28", "Bike #": "363", "Zip Code": "94103", "Start Terminal": "62", "End Station": "5th at Howard", "Start Station": "2nd at Folsom", "Duration": "309", "Start Date": "1/5/2014 9:22", "Trip ID": "142796", "End Terminal": "57"}, {"Subscription Type": "Subscriber", "End Date": "1/5/2014 9:34", "Bike #": "377", "Zip Code": "94102", "Start Terminal": "53", "End Station": "Powell Street BART", "Start Station": "Powell Street BART", "Duration": "661", "Start Date": "1/5/2014 9:23", "Trip ID": "142797", "End Terminal": "53"}, {"Subscription Type": "Subscriber", "End Date": "1/5/2014 9:29", "Bike #": "361", "Zip Code": "94105", "Start Terminal": "49", "End Station": "2nd at South Park", "Start Station": "Spear at Folsom", "Duration": "333", "Start Date": "1/5/2014 9:23", "Trip ID": "142798", "End Terminal": "64"}, {"Subscription Type": "Customer", "End Date": "1/5/2014 9:42", "Bike #": "503", "Zip Code": "93924", "Start Terminal": "73", "End Station": "Powell at Post (Union Square)", "Start Station": "Grant Avenue at Columbus Avenue", "Duration": "910", "Start Date": "1/5/2014 9:27", "Trip ID": "142800", "End Terminal": "71"}, {"Subscription Type": "Subscriber", "End Date": "1/5/2014 9:54", "Bike #": "290", "Zip Code": "94105", "Start Terminal": "63", "End Station": "Market at 4th", "Start Station": "Howard at 2nd", "Duration": "518", "Start Date": "1/5/2014 9:45", "Trip ID": "142802", "End Terminal": "76"}, {"Subscription Type": "Subscriber", "End Date": "1/5/2014 10:00", "Bike #": "510", "Zip Code": "94158", "Start Terminal": "70", "End Station": "Market at Sansome", "Start Station": "San Francisco Caltrain (Townsend at 4th)", "Duration": "561", "Start Date": "1/5/2014 9:50", "Trip ID": "142803", "End Terminal": "77"}, {"Subscription Type": "Subscriber", "End Date": "1/5/2014 9:59", "Bike #": "596", "Zip Code": "94105", "Start Terminal": "54", "End Station": "2nd at Townsend", "Start Station": "Embarcadero at Bryant", "Duration": "267", "Start Date": "1/5/2014 9:55", "Trip ID": "142804", "End Terminal": "61"}, {"Subscription Type": "Subscriber", "End Date": "1/5/2014 10:03", "Bike #": "439", "Zip Code": "94105", "Start Terminal": "62", "End Station": "Powell Street BART", "Start Station": "2nd at Folsom", "Duration": "423", "Start Date": "1/5/2014 9:56", "Trip ID": "142808", "End Terminal": "53"}, {"Subscription Type": "Subscriber", "End Date": "1/5/2014 10:04", "Bike #": "523", "Zip Code": "95815", "Start Terminal": "74", "End Station": "Market at 4th", "Start Station": "Steuart at Market", "Duration": "390", "Start Date": "1/5/2014 9:57", "Trip ID": "142809", "End Terminal": "76"}, {"Subscription Type": "Customer", "End Date": "1/5/2014 10:12", "Bike #": "396", "Zip Code": "94133", "Start Terminal": "45", "End Station": "2nd at South Park", "Start Station": "Commercial at Montgomery", "Duration": "514", "Start Date": "1/5/2014 10:03", "Trip ID": "142810", "End Terminal": "64"}, {"Subscription Type": "Subscriber", "End Date": "1/5/2014 10:14", "Bike #": "361", "Zip Code": "94107", "Start Terminal": "64", "End Station": "Yerba Buena Center of the Arts (3rd @ Howard)", "Start Station": "2nd at South Park", "Duration": "277", "Start Date": "1/5/2014 10:09", "Trip ID": "142811", "End Terminal": "68"}, {"Subscription Type": "Subscriber", "End Date": "1/5/2014 10:22", "Bike #": "526", "Zip Code": "94105", "Start Terminal": "63", "End Station": "Yerba Buena Center of the Arts (3rd @ Howard)", "Start Station": "Howard at 2nd", "Duration": "132", "Start Date": "1/5/2014 10:20", "Trip ID": "142813", "End Terminal": "68"}, {"Subscription Type": "Subscriber", "End Date": "1/5/2014 10:33", "Bike #": "554", "Zip Code": "94107", "Start Terminal": "70", "End Station": "5th at Howard", "Start Station": "San Francisco Caltrain (Townsend at 4th)", "Duration": "394", "Start Date": "1/5/2014 10:26", "Trip ID": "142819", "End Terminal": "57"}, {"Subscription Type": "Subscriber", "End Date": "1/5/2014 10:37", "Bike #": "713", "Zip Code": "94041", "Start Terminal": "32", "End Station": "Mountain View Caltrain Station", "Start Station": "Castro Street and El Camino Real", "Duration": "388", "Start Date": "1/5/2014 10:31", "Trip ID": "142820", "End Terminal": "28"}, {"Subscription Type": "Customer", "End Date": "1/5/2014 10:37", "Bike #": "524", "Zip Code": "94117", "Start Terminal": "46", "End Station": "Commercial at Montgomery", "Start Station": "Washington at Kearney", "Duration": "108", "Start Date": "1/5/2014 10:35", "Trip ID": "142821", "End Terminal": "45"}, {"Subscription Type": "Subscriber", "End Date": "1/5/2014 10:46", "Bike #": "550", "Zip Code": "94105", "Start Terminal": "49", "End Station": "Embarcadero at Sansome", "Start Station": "Spear at Folsom", "Duration": "647", "Start Date": "1/5/2014 10:35", "Trip ID": "142822", "End Terminal": "60"}, {"Subscription Type": "Subscriber", "End Date": "1/5/2014 10:47", "Bike #": "499", "Zip Code": "94105", "Start Terminal": "51", "End Station": "Mechanics Plaza (Market at Battery)", "Start Station": "Embarcadero at Folsom", "Duration": "400", "Start Date": "1/5/2014 10:41", "Trip ID": "142824", "End Terminal": "75"}, {"Subscription Type": "Subscriber", "End Date": "1/5/2014 10:47", "Bike #": "636", "Zip Code": "94105", "Start Terminal": "51", "End Station": "Mechanics Plaza (Market at Battery)", "Start Station": "Embarcadero at Folsom", "Duration": "371", "Start Date": "1/5/2014 10:41", "Trip ID": "142825", "End Terminal": "75"}, {"Subscription Type": "Subscriber", "End Date": "1/5/2014 10:53", "Bike #": "713", "Zip Code": "94041", "Start Terminal": "28", "End Station": "Mountain View City Hall", "Start Station": "Mountain View Caltrain Station", "Duration": "302", "Start Date": "1/5/2014 10:48", "Trip ID": "142826", "End Terminal": "27"}, {"Subscription Type": "Subscriber", "End Date": "1/5/2014 11:01", "Bike #": "385", "Zip Code": "94103", "Start Terminal": "66", "End Station": "Market at Sansome", "Start Station": "South Van Ness at Market", "Duration": "755", "Start Date": "1/5/2014 10:48", "Trip ID": "142827", "End Terminal": "77"}, {"Subscription Type": "Subscriber", "End Date": "1/5/2014 11:02", "Bike #": "250", "Zip Code": "94040", "Start Terminal": "33", "End Station": "Mountain View Caltrain Station", "Start Station": "Rengstorff Avenue / California Street", "Duration": "769", "Start Date": "1/5/2014 10:49", "Trip ID": "142828", "End Terminal": "28"}, {"Subscription Type": "Customer", "End Date": "1/5/2014 11:02", "Bike #": "613", "Zip Code": "60661", "Start Terminal": "41", "End Station": "Powell at Post (Union Square)", "Start Station": "Clay at Battery", "Duration": "497", "Start Date": "1/5/2014 10:54", "Trip ID": "142832", "End Terminal": "71"}, {"Subscription Type": "Subscriber", "End Date": "1/5/2014 11:28", "Bike #": "483", "Zip Code": "94105", "Start Terminal": "54", "End Station": "Embarcadero at Bryant", "Start Station": "Embarcadero at Bryant", "Duration": "1614", "Start Date": "1/5/2014 11:01", "Trip ID": "142833", "End Terminal": "54"}, {"Subscription Type": "Subscriber", "End Date": "1/5/2014 11:28", "Bike #": "604", "Zip Code": "95139", "Start Terminal": "54", "End Station": "Embarcadero at Bryant", "Start Station": "Embarcadero at Bryant", "Duration": "1620", "Start Date": "1/5/2014 11:01", "Trip ID": "142834", "End Terminal": "54"}, {"Subscription Type": "Customer", "End Date": "1/5/2014 11:45", "Bike #": "619", "Zip Code": "93924", "Start Terminal": "71", "End Station": "Harry Bridges Plaza (Ferry Building)", "Start Station": "Powell at Post (Union Square)", "Duration": "2628", "Start Date": "1/5/2014 11:01", "Trip ID": "142835", "End Terminal": "50"}, {"Subscription Type": "Subscriber", "End Date": "1/5/2014 11:10", "Bike #": "521", "Zip Code": "94133", "Start Terminal": "73", "End Station": "Powell at Post (Union Square)", "Start Station": "Grant Avenue at Columbus Avenue", "Duration": "366", "Start Date": "1/5/2014 11:04", "Trip ID": "142836", "End Terminal": "71"}, {"Subscription Type": "Subscriber", "End Date": "1/5/2014 11:25", "Bike #": "480", "Zip Code": "94105", "Start Terminal": "72", "End Station": "Embarcadero at Bryant", "Start Station": "Civic Center BART (7th at Market)", "Duration": "958", "Start Date": "1/5/2014 11:09", "Trip ID": "142837", "End Terminal": "54"}, {"Subscription Type": "Customer", "End Date": "1/5/2014 11:18", "Bike #": "417", "Zip Code": "", "Start Terminal": "50", "End Station": "Spear at Folsom", "Start Station": "Harry Bridges Plaza (Ferry Building)", "Duration": "421", "Start Date": "1/5/2014 11:11", "Trip ID": "142839", "End Terminal": "49"}, {"Subscription Type": "Subscriber", "End Date": "1/5/2014 11:16", "Bike #": "546", "Zip Code": "94133", "Start Terminal": "68", "End Station": "Grant Avenue at Columbus Avenue", "Start Station": "Yerba Buena Center of the Arts (3rd @ Howard)", "Duration": "451", "Start Date": "1/5/2014 11:08", "Trip ID": "142840", "End Terminal": "73"}, {"Subscription Type": "Customer", "End Date": "1/5/2014 11:30", "Bike #": "281", "Zip Code": "1757", "Start Terminal": "41", "End Station": "2nd at Townsend", "Start Station": "Clay at Battery", "Duration": "1012", "Start Date": "1/5/2014 11:13", "Trip ID": "142841", "End Terminal": "61"}, {"Subscription Type": "Customer", "End Date": "1/5/2014 11:30", "Bike #": "399", "Zip Code": "1757", "Start Terminal": "41", "End Station": "2nd at Townsend", "Start Station": "Clay at Battery", "Duration": "985", "Start Date": "1/5/2014 11:13", "Trip ID": "142842", "End Terminal": "61"}, {"Subscription Type": "Subscriber", "End Date": "1/5/2014 11:40", "Bike #": "516", "Zip Code": "94102", "Start Terminal": "61", "End Station": "South Van Ness at Market", "Start Station": "2nd at Townsend", "Duration": "1360", "Start Date": "1/5/2014 11:18", "Trip ID": "142843", "End Terminal": "66"}, {"Subscription Type": "Customer", "End Date": "1/5/2014 11:29", "Bike #": "615", "Zip Code": "94129", "Start Terminal": "41", "End Station": "Post at Kearney", "Start Station": "Clay at Battery", "Duration": "414", "Start Date": "1/5/2014 11:22", "Trip ID": "142844", "End Terminal": "47"}, {"Subscription Type": "Subscriber", "End Date": "1/5/2014 11:57", "Bike #": "310", "Zip Code": "94105", "Start Terminal": "63", "End Station": "Powell Street BART", "Start Station": "Howard at 2nd", "Duration": "2094", "Start Date": "1/5/2014 11:22", "Trip ID": "142845", "End Terminal": "53"}, {"Subscription Type": "Subscriber", "End Date": "1/5/2014 11:46", "Bike #": "401", "Zip Code": "94110", "Start Terminal": "66", "End Station": "Harry Bridges Plaza (Ferry Building)", "Start Station": "South Van Ness at Market", "Duration": "1315", "Start Date": "1/5/2014 11:24", "Trip ID": "142846", "End Terminal": "50"}, {"Subscription Type": "Customer", "End Date": "1/5/2014 11:56", "Bike #": "390", "Zip Code": "89701", "Start Terminal": "48", "End Station": "Embarcadero at Vallejo", "Start Station": "Embarcadero at Vallejo", "Duration": "1871", "Start Date": "1/5/2014 11:25", "Trip ID": "142848", "End Terminal": "48"}, {"Subscription Type": "Customer", "End Date": "1/5/2014 11:55", "Bike #": "391", "Zip Code": "89701", "Start Terminal": "48", "End Station": "Embarcadero at Vallejo", "Start Station": "Embarcadero at Vallejo", "Duration": "1774", "Start Date": "1/5/2014 11:26", "Trip ID": "142849", "End Terminal": "48"}, {"Subscription Type": "Customer", "End Date": "1/5/2014 11:48", "Bike #": "79", "Zip Code": "10026", "Start Terminal": "29", "End Station": "California Ave Caltrain Station", "Start Station": "San Antonio Caltrain Station", "Duration": "1089", "Start Date": "1/5/2014 11:30", "Trip ID": "142850", "End Terminal": "36"}, {"Subscription Type": "Subscriber", "End Date": "1/5/2014 11:47", "Bike #": "482", "Zip Code": "94608", "Start Terminal": "55", "End Station": "Washington at Kearney", "Start Station": "Temporary Transbay Terminal (Howard at Beale)", "Duration": "726", "Start Date": "1/5/2014 11:35", "Trip ID": "142853", "End Terminal": "46"}, {"Subscription Type": "Subscriber", "End Date": "1/5/2014 11:51", "Bike #": "574", "Zip Code": "94102", "Start Terminal": "72", "End Station": "Embarcadero at Sansome", "Start Station": "Civic Center BART (7th at Market)", "Duration": "944", "Start Date": "1/5/2014 11:36", "Trip ID": "142854", "End Terminal": "60"}, {"Subscription Type": "Subscriber", "End Date": "1/5/2014 11:38", "Bike #": "432", "Zip Code": "94609", "Start Terminal": "74", "End Station": "Embarcadero at Folsom", "Start Station": "Steuart at Market", "Duration": "109", "Start Date": "1/5/2014 11:36", "Trip ID": "142856", "End Terminal": "51"}, {"Subscription Type": "Subscriber", "End Date": "1/5/2014 11:42", "Bike #": "381", "Zip Code": "94111", "Start Terminal": "77", "End Station": "Commercial at Montgomery", "Start Station": "Market at Sansome", "Duration": "354", "Start Date": "1/5/2014 11:36", "Trip ID": "142857", "End Terminal": "45"}, {"Subscription Type": "Subscriber", "End Date": "1/5/2014 11:46", "Bike #": "332", "Zip Code": "94111", "Start Terminal": "45", "End Station": "Harry Bridges Plaza (Ferry Building)", "Start Station": "Commercial at Montgomery", "Duration": "302", "Start Date": "1/5/2014 11:41", "Trip ID": "142861", "End Terminal": "50"}, {"Subscription Type": "Subscriber", "End Date": "1/5/2014 11:50", "Bike #": "542", "Zip Code": "94105", "Start Terminal": "63", "End Station": "Grant Avenue at Columbus Avenue", "Start Station": "Howard at 2nd", "Duration": "563", "Start Date": "1/5/2014 11:41", "Trip ID": "142862", "End Terminal": "73"}, {"Subscription Type": "Subscriber", "End Date": "1/5/2014 11:53", "Bike #": "506", "Zip Code": "94133", "Start Terminal": "73", "End Station": "Spear at Folsom", "Start Station": "Grant Avenue at Columbus Avenue", "Duration": "639", "Start Date": "1/5/2014 11:42", "Trip ID": "142863", "End Terminal": "49"}, {"Subscription Type": "Subscriber", "End Date": "1/5/2014 11:52", "Bike #": "417", "Zip Code": "94105", "Start Terminal": "49", "End Station": "2nd at Townsend", "Start Station": "Spear at Folsom", "Duration": "379", "Start Date": "1/5/2014 11:46", "Trip ID": "142864", "End Terminal": "61"}, {"Subscription Type": "Subscriber", "End Date": "1/5/2014 12:00", "Bike #": "501", "Zip Code": "94107", "Start Terminal": "61", "End Station": "Market at 4th", "Start Station": "2nd at Townsend", "Duration": "613", "Start Date": "1/5/2014 11:50", "Trip ID": "142866", "End Terminal": "76"}, {"Subscription Type": "Subscriber", "End Date": "1/5/2014 12:14", "Bike #": "689", "Zip Code": "94040", "Start Terminal": "29", "End Station": "Mountain View Caltrain Station", "Start Station": "San Antonio Caltrain Station", "Duration": "1363", "Start Date": "1/5/2014 11:51", "Trip ID": "142867", "End Terminal": "28"}, {"Subscription Type": "Customer", "End Date": "1/5/2014 12:08", "Bike #": "60", "Zip Code": "8504", "Start Terminal": "12", "End Station": "SJSU 4th at San Carlos", "Start Station": "SJSU 4th at San Carlos", "Duration": "834", "Start Date": "1/5/2014 11:54", "Trip ID": "142869", "End Terminal": "12"}, {"Subscription Type": "Customer", "End Date": "1/5/2014 12:07", "Bike #": "202", "Zip Code": "8504", "Start Terminal": "12", "End Station": "SJSU 4th at San Carlos", "Start Station": "SJSU 4th at San Carlos", "Duration": "743", "Start Date": "1/5/2014 11:54", "Trip ID": "142870", "End Terminal": "12"}, {"Subscription Type": "Subscriber", "End Date": "1/5/2014 12:07", "Bike #": "483", "Zip Code": "94105", "Start Terminal": "54", "End Station": "Embarcadero at Sansome", "Start Station": "Embarcadero at Bryant", "Duration": "706", "Start Date": "1/5/2014 11:56", "Trip ID": "142873", "End Terminal": "60"}, {"Subscription Type": "Subscriber", "End Date": "1/5/2014 12:08", "Bike #": "604", "Zip Code": "95139", "Start Terminal": "54", "End Station": "Embarcadero at Sansome", "Start Station": "Embarcadero at Bryant", "Duration": "711", "Start Date": "1/5/2014 11:56", "Trip ID": "142874", "End Terminal": "60"}, {"Subscription Type": "Subscriber", "End Date": "1/5/2014 12:13", "Bike #": "332", "Zip Code": "94111", "Start Terminal": "50", "End Station": "Commercial at Montgomery", "Start Station": "Harry Bridges Plaza (Ferry Building)", "Duration": "971", "Start Date": "1/5/2014 11:56", "Trip ID": "142875", "End Terminal": "45"}, {"Subscription Type": "Customer", "End Date": "1/5/2014 12:08", "Bike #": "10", "Zip Code": "8102", "Start Terminal": "12", "End Station": "SJSU 4th at San Carlos", "Start Station": "SJSU 4th at San Carlos", "Duration": "595", "Start Date": "1/5/2014 11:58", "Trip ID": "142876", "End Terminal": "12"}, {"Subscription Type": "Subscriber", "End Date": "1/5/2014 12:21", "Bike #": "361", "Zip Code": "94105", "Start Terminal": "68", "End Station": "Temporary Transbay Terminal (Howard at Beale)", "Start Station": "Yerba Buena Center of the Arts (3rd @ Howard)", "Duration": "1386", "Start Date": "1/5/2014 11:58", "Trip ID": "142877", "End Terminal": "55"}, {"Subscription Type": "Subscriber", "End Date": "1/5/2014 12:08", "Bike #": "418", "Zip Code": "94103", "Start Terminal": "55", "End Station": "Harry Bridges Plaza (Ferry Building)", "Start Station": "Temporary Transbay Terminal (Howard at Beale)", "Duration": "507", "Start Date": "1/5/2014 11:59", "Trip ID": "142879", "End Terminal": "50"}, {"Subscription Type": "Subscriber", "End Date": "1/5/2014 12:11", "Bike #": "370", "Zip Code": "94608", "Start Terminal": "46", "End Station": "Temporary Transbay Terminal (Howard at Beale)", "Start Station": "Washington at Kearney", "Duration": "660", "Start Date": "1/5/2014 12:00", "Trip ID": "142880", "End Terminal": "55"}, {"Subscription Type": "Subscriber", "End Date": "1/5/2014 12:04", "Bike #": "280", "Zip Code": "94108", "Start Terminal": "75", "End Station": "Clay at Battery", "Start Station": "Mechanics Plaza (Market at Battery)", "Duration": "197", "Start Date": "1/5/2014 12:01", "Trip ID": "142882", "End Terminal": "41"}, {"Subscription Type": "Subscriber", "End Date": "1/5/2014 12:13", "Bike #": "439", "Zip Code": "94105", "Start Terminal": "53", "End Station": "2nd at Folsom", "Start Station": "Powell Street BART", "Duration": "614", "Start Date": "1/5/2014 12:03", "Trip ID": "142883", "End Terminal": "62"}, {"Subscription Type": "Customer", "End Date": "1/5/2014 12:07", "Bike #": "88", "Zip Code": "8030", "Start Terminal": "12", "End Station": "SJSU 4th at San Carlos", "Start Station": "SJSU 4th at San Carlos", "Duration": "253", "Start Date": "1/5/2014 12:03", "Trip ID": "142884", "End Terminal": "12"}, {"Subscription Type": "Customer", "End Date": "1/5/2014 12:11", "Bike #": "359", "Zip Code": "94129", "Start Terminal": "47", "End Station": "Clay at Battery", "Start Station": "Post at Kearney", "Duration": "430", "Start Date": "1/5/2014 12:03", "Trip ID": "142885", "End Terminal": "41"}, {"Subscription Type": "Customer", "End Date": "1/5/2014 12:34", "Bike #": "245", "Zip Code": "8102", "Start Terminal": "12", "End Station": "MLK Library", "Start Station": "SJSU 4th at San Carlos", "Duration": "1719", "Start Date": "1/5/2014 12:05", "Trip ID": "142886", "End Terminal": "11"}, {"Subscription Type": "Customer", "End Date": "1/5/2014 12:18", "Bike #": "92", "Zip Code": "8102", "Start Terminal": "12", "End Station": "SJSU 4th at San Carlos", "Start Station": "SJSU 4th at San Carlos", "Duration": "617", "Start Date": "1/5/2014 12:07", "Trip ID": "142889", "End Terminal": "12"}, {"Subscription Type": "Subscriber", "End Date": "1/5/2014 12:20", "Bike #": "556", "Zip Code": "94107", "Start Terminal": "53", "End Station": "2nd at South Park", "Start Station": "Powell Street BART", "Duration": "695", "Start Date": "1/5/2014 12:08", "Trip ID": "142890", "End Terminal": "64"}, {"Subscription Type": "Customer", "End Date": "1/5/2014 12:28", "Bike #": "274", "Zip Code": "93924", "Start Terminal": "50", "End Station": "Powell at Post (Union Square)", "Start Station": "Harry Bridges Plaza (Ferry Building)", "Duration": "1107", "Start Date": "1/5/2014 12:10", "Trip ID": "142891", "End Terminal": "71"}, {"Subscription Type": "Customer", "End Date": "1/5/2014 12:29", "Bike #": "60", "Zip Code": "8504", "Start Terminal": "12", "End Station": "MLK Library", "Start Station": "SJSU 4th at San Carlos", "Duration": "1149", "Start Date": "1/5/2014 12:09", "Trip ID": "142892", "End Terminal": "11"}, {"Subscription Type": "Customer", "End Date": "1/5/2014 12:24", "Bike #": "202", "Zip Code": "8504", "Start Terminal": "12", "End Station": "MLK Library", "Start Station": "SJSU 4th at San Carlos", "Duration": "893", "Start Date": "1/5/2014 12:10", "Trip ID": "142893", "End Terminal": "11"}, {"Subscription Type": "Subscriber", "End Date": "1/5/2014 12:18", "Bike #": "401", "Zip Code": "94110", "Start Terminal": "50", "End Station": "Yerba Buena Center of the Arts (3rd @ Howard)", "Start Station": "Harry Bridges Plaza (Ferry Building)", "Duration": "455", "Start Date": "1/5/2014 12:11", "Trip ID": "142894", "End Terminal": "68"}, {"Subscription Type": "Customer", "End Date": "1/5/2014 12:20", "Bike #": "88", "Zip Code": "8030", "Start Terminal": "12", "End Station": "SJSU 4th at San Carlos", "Start Station": "SJSU 4th at San Carlos", "Duration": "534", "Start Date": "1/5/2014 12:11", "Trip ID": "142895", "End Terminal": "12"}, {"Subscription Type": "Customer", "End Date": "1/5/2014 12:38", "Bike #": "273", "Zip Code": "78731", "Start Terminal": "58", "End Station": "Market at 4th", "Start Station": "San Francisco City Hall", "Duration": "1358", "Start Date": "1/5/2014 12:15", "Trip ID": "142897", "End Terminal": "76"}, {"Subscription Type": "Subscriber", "End Date": "1/5/2014 12:26", "Bike #": "361", "Zip Code": "94105", "Start Terminal": "55", "End Station": "Clay at Battery", "Start Station": "Temporary Transbay Terminal (Howard at Beale)", "Duration": "267", "Start Date": "1/5/2014 12:22", "Trip ID": "142900", "End Terminal": "41"}, {"Subscription Type": "Subscriber", "End Date": "1/5/2014 12:32", "Bike #": "431", "Zip Code": "94107", "Start Terminal": "69", "End Station": "2nd at South Park", "Start Station": "San Francisco Caltrain 2 (330 Townsend)", "Duration": "361", "Start Date": "1/5/2014 12:26", "Trip ID": "142901", "End Terminal": "64"}, {"Subscription Type": "Subscriber", "End Date": "1/5/2014 14:50", "Bike #": "443", "Zip Code": "94107", "Start Terminal": "69", "End Station": "San Francisco Caltrain 2 (330 Townsend)", "Start Station": "San Francisco Caltrain 2 (330 Townsend)", "Duration": "8635", "Start Date": "1/5/2014 12:26", "Trip ID": "142903", "End Terminal": "69"}, {"Subscription Type": "Customer", "End Date": "1/5/2014 12:50", "Bike #": "109", "Zip Code": "8102", "Start Terminal": "11", "End Station": "Santa Clara at Almaden", "Start Station": "MLK Library", "Duration": "1278", "Start Date": "1/5/2014 12:29", "Trip ID": "142904", "End Terminal": "4"}, {"Subscription Type": "Customer", "End Date": "1/5/2014 14:19", "Bike #": "167", "Zip Code": "94301", "Start Terminal": "36", "End Station": "California Ave Caltrain Station", "Start Station": "California Ave Caltrain Station", "Duration": "6561", "Start Date": "1/5/2014 12:30", "Trip ID": "142905", "End Terminal": "36"}, {"Subscription Type": "Customer", "End Date": "1/5/2014 12:50", "Bike #": "211", "Zip Code": "8030", "Start Terminal": "11", "End Station": "Santa Clara at Almaden", "Start Station": "MLK Library", "Duration": "1161", "Start Date": "1/5/2014 12:31", "Trip ID": "142906", "End Terminal": "4"}, {"Subscription Type": "Customer", "End Date": "1/5/2014 12:50", "Bike #": "145", "Zip Code": "8102", "Start Terminal": "11", "End Station": "Santa Clara at Almaden", "Start Station": "MLK Library", "Duration": "1158", "Start Date": "1/5/2014 12:31", "Trip ID": "142907", "End Terminal": "4"}, {"Subscription Type": "Customer", "End Date": "1/5/2014 12:50", "Bike #": "60", "Zip Code": "8504", "Start Terminal": "11", "End Station": "Santa Clara at Almaden", "Start Station": "MLK Library", "Duration": "1094", "Start Date": "1/5/2014 12:32", "Trip ID": "142908", "End Terminal": "4"}, {"Subscription Type": "Customer", "End Date": "1/5/2014 12:50", "Bike #": "202", "Zip Code": "8102", "Start Terminal": "11", "End Station": "Santa Clara at Almaden", "Start Station": "MLK Library", "Duration": "939", "Start Date": "1/5/2014 12:35", "Trip ID": "142909", "End Terminal": "4"}, {"Subscription Type": "Customer", "End Date": "1/5/2014 12:39", "Bike #": "279", "Zip Code": "75002", "Start Terminal": "69", "End Station": "Townsend at 7th", "Start Station": "San Francisco Caltrain 2 (330 Townsend)", "Duration": "233", "Start Date": "1/5/2014 12:35", "Trip ID": "142910", "End Terminal": "65"}, {"Subscription Type": "Customer", "End Date": "1/5/2014 12:46", "Bike #": "361", "Zip Code": "64081", "Start Terminal": "41", "End Station": "Market at 4th", "Start Station": "Clay at Battery", "Duration": "543", "Start Date": "1/5/2014 12:37", "Trip ID": "142911", "End Terminal": "76"}, {"Subscription Type": "Subscriber", "End Date": "1/5/2014 12:51", "Bike #": "424", "Zip Code": "94107", "Start Terminal": "65", "End Station": "Yerba Buena Center of the Arts (3rd @ Howard)", "Start Station": "Townsend at 7th", "Duration": "693", "Start Date": "1/5/2014 12:39", "Trip ID": "142912", "End Terminal": "68"}, {"Subscription Type": "Subscriber", "End Date": "1/5/2014 12:52", "Bike #": "550", "Zip Code": "94133", "Start Terminal": "60", "End Station": "2nd at Townsend", "Start Station": "Embarcadero at Sansome", "Duration": "658", "Start Date": "1/5/2014 12:41", "Trip ID": "142913", "End Terminal": "61"}, {"Subscription Type": "Subscriber", "End Date": "1/5/2014 12:44", "Bike #": "441", "Zip Code": "94105", "Start Terminal": "51", "End Station": "Harry Bridges Plaza (Ferry Building)", "Start Station": "Embarcadero at Folsom", "Duration": "194", "Start Date": "1/5/2014 12:41", "Trip ID": "142914", "End Terminal": "50"}, {"Subscription Type": "Subscriber", "End Date": "1/5/2014 12:56", "Bike #": "402", "Zip Code": "94107", "Start Terminal": "75", "End Station": "Market at 4th", "Start Station": "Mechanics Plaza (Market at Battery)", "Duration": "244", "Start Date": "1/5/2014 12:52", "Trip ID": "142920", "End Terminal": "76"}, {"Subscription Type": "Subscriber", "End Date": "1/5/2014 13:09", "Bike #": "689", "Zip Code": "94040", "Start Terminal": "28", "End Station": "Rengstorff Avenue / California Street", "Start Station": "Mountain View Caltrain Station", "Duration": "1028", "Start Date": "1/5/2014 12:52", "Trip ID": "142921", "End Terminal": "33"}, {"Subscription Type": "Customer", "End Date": "1/5/2014 13:22", "Bike #": "313", "Zip Code": "1757", "Start Terminal": "61", "End Station": "Market at Sansome", "Start Station": "2nd at Townsend", "Duration": "1608", "Start Date": "1/5/2014 12:56", "Trip ID": "142925", "End Terminal": "77"}, {"Subscription Type": "Customer", "End Date": "1/5/2014 13:22", "Bike #": "596", "Zip Code": "1757", "Start Terminal": "61", "End Station": "Market at Sansome", "Start Station": "2nd at Townsend", "Duration": "1567", "Start Date": "1/5/2014 12:56", "Trip ID": "142926", "End Terminal": "77"}, {"Subscription Type": "Customer", "End Date": "1/5/2014 13:18", "Bike #": "317", "Zip Code": "94107", "Start Terminal": "62", "End Station": "Embarcadero at Vallejo", "Start Station": "2nd at Folsom", "Duration": "1333", "Start Date": "1/5/2014 12:56", "Trip ID": "142927", "End Terminal": "48"}, {"Subscription Type": "Subscriber", "End Date": "1/5/2014 13:08", "Bike #": "370", "Zip Code": "94103", "Start Terminal": "55", "End Station": "5th at Howard", "Start Station": "Temporary Transbay Terminal (Howard at Beale)", "Duration": "636", "Start Date": "1/5/2014 12:57", "Trip ID": "142928", "End Terminal": "57"}, {"Subscription Type": "Subscriber", "End Date": "1/5/2014 13:04", "Bike #": "457", "Zip Code": "94105", "Start Terminal": "49", "End Station": "Yerba Buena Center of the Arts (3rd @ Howard)", "Start Station": "Spear at Folsom", "Duration": "425", "Start Date": "1/5/2014 12:57", "Trip ID": "142929", "End Terminal": "68"}, {"Subscription Type": "Customer", "End Date": "1/5/2014 13:20", "Bike #": "79", "Zip Code": "10026", "Start Terminal": "36", "End Station": "San Antonio Caltrain Station", "Start Station": "California Ave Caltrain Station", "Duration": "1116", "Start Date": "1/5/2014 13:01", "Trip ID": "142930", "End Terminal": "29"}, {"Subscription Type": "Subscriber", "End Date": "1/5/2014 13:15", "Bike #": "465", "Zip Code": "94122", "Start Terminal": "72", "End Station": "San Francisco Caltrain (Townsend at 4th)", "Start Station": "Civic Center BART (7th at Market)", "Duration": "690", "Start Date": "1/5/2014 13:04", "Trip ID": "142932", "End Terminal": "70"}, {"Subscription Type": "Subscriber", "End Date": "1/5/2014 13:07", "Bike #": "522", "Zip Code": "94609", "Start Terminal": "51", "End Station": "Steuart at Market", "Start Station": "Embarcadero at Folsom", "Duration": "115", "Start Date": "1/5/2014 13:05", "Trip ID": "142933", "End Terminal": "74"}, {"Subscription Type": "Subscriber", "End Date": "1/5/2014 13:14", "Bike #": "404", "Zip Code": "94105", "Start Terminal": "62", "End Station": "Embarcadero at Bryant", "Start Station": "2nd at Folsom", "Duration": "379", "Start Date": "1/5/2014 13:08", "Trip ID": "142934", "End Terminal": "54"}, {"Subscription Type": "Subscriber", "End Date": "1/5/2014 13:31", "Bike #": "689", "Zip Code": "94040", "Start Terminal": "33", "End Station": "San Antonio Caltrain Station", "Start Station": "Rengstorff Avenue / California Street", "Duration": "1119", "Start Date": "1/5/2014 13:13", "Trip ID": "142936", "End Terminal": "29"}, {"Subscription Type": "Customer", "End Date": "1/5/2014 13:37", "Bike #": "376", "Zip Code": "", "Start Terminal": "75", "End Station": "Harry Bridges Plaza (Ferry Building)", "Start Station": "Mechanics Plaza (Market at Battery)", "Duration": "1264", "Start Date": "1/5/2014 13:16", "Trip ID": "142937", "End Terminal": "50"}, {"Subscription Type": "Customer", "End Date": "1/5/2014 13:37", "Bike #": "573", "Zip Code": "", "Start Terminal": "75", "End Station": "Harry Bridges Plaza (Ferry Building)", "Start Station": "Mechanics Plaza (Market at Battery)", "Duration": "1214", "Start Date": "1/5/2014 13:17", "Trip ID": "142938", "End Terminal": "50"}, {"Subscription Type": "Subscriber", "End Date": "1/5/2014 13:25", "Bike #": "375", "Zip Code": "94111", "Start Terminal": "60", "End Station": "Embarcadero at Folsom", "Start Station": "Embarcadero at Sansome", "Duration": "458", "Start Date": "1/5/2014 13:17", "Trip ID": "142940", "End Terminal": "51"}, {"Subscription Type": "Customer", "End Date": "1/5/2014 13:22", "Bike #": "279", "Zip Code": "75002", "Start Terminal": "65", "End Station": "San Francisco Caltrain (Townsend at 4th)", "Start Station": "Townsend at 7th", "Duration": "285", "Start Date": "1/5/2014 13:17", "Trip ID": "142941", "End Terminal": "70"}, {"Subscription Type": "Subscriber", "End Date": "1/5/2014 13:24", "Bike #": "450", "Zip Code": "94111", "Start Terminal": "60", "End Station": "Embarcadero at Folsom", "Start Station": "Embarcadero at Sansome", "Duration": "398", "Start Date": "1/5/2014 13:18", "Trip ID": "142942", "End Terminal": "51"}, {"Subscription Type": "Subscriber", "End Date": "1/5/2014 13:28", "Bike #": "370", "Zip Code": "94103", "Start Terminal": "57", "End Station": "Market at 10th", "Start Station": "5th at Howard", "Duration": "636", "Start Date": "1/5/2014 13:18", "Trip ID": "142943", "End Terminal": "67"}, {"Subscription Type": "Customer", "End Date": "1/5/2014 13:37", "Bike #": "600", "Zip Code": "", "Start Terminal": "75", "End Station": "Harry Bridges Plaza (Ferry Building)", "Start Station": "Mechanics Plaza (Market at Battery)", "Duration": "1011", "Start Date": "1/5/2014 13:20", "Trip ID": "142945", "End Terminal": "50"}, {"Subscription Type": "Customer", "End Date": "1/5/2014 13:36", "Bike #": "591", "Zip Code": "", "Start Terminal": "75", "End Station": "Harry Bridges Plaza (Ferry Building)", "Start Station": "Mechanics Plaza (Market at Battery)", "Duration": "976", "Start Date": "1/5/2014 13:20", "Trip ID": "142946", "End Terminal": "50"}, {"Subscription Type": "Subscriber", "End Date": "1/5/2014 13:23", "Bike #": "416", "Zip Code": "94105", "Start Terminal": "62", "End Station": "Howard at 2nd", "Start Station": "2nd at Folsom", "Duration": "86", "Start Date": "1/5/2014 13:21", "Trip ID": "142947", "End Terminal": "63"}, {"Subscription Type": "Subscriber", "End Date": "1/5/2014 13:41", "Bike #": "425", "Zip Code": "94133", "Start Terminal": "73", "End Station": "South Van Ness at Market", "Start Station": "Grant Avenue at Columbus Avenue", "Duration": "992", "Start Date": "1/5/2014 13:25", "Trip ID": "142948", "End Terminal": "66"}, {"Subscription Type": "Subscriber", "End Date": "1/5/2014 13:34", "Bike #": "536", "Zip Code": "94105", "Start Terminal": "50", "End Station": "Embarcadero at Bryant", "Start Station": "Harry Bridges Plaza (Ferry Building)", "Duration": "468", "Start Date": "1/5/2014 13:26", "Trip ID": "142949", "End Terminal": "54"}, {"Subscription Type": "Subscriber", "End Date": "1/5/2014 13:36", "Bike #": "402", "Zip Code": "94107", "Start Terminal": "76", "End Station": "Davis at Jackson", "Start Station": "Market at 4th", "Duration": "583", "Start Date": "1/5/2014 13:26", "Trip ID": "142950", "End Terminal": "42"}, {"Subscription Type": "Subscriber", "End Date": "1/5/2014 13:32", "Bike #": "207", "Zip Code": "95113", "Start Terminal": "6", "End Station": "San Jose City Hall", "Start Station": "San Pedro Square", "Duration": "237", "Start Date": "1/5/2014 13:28", "Trip ID": "142951", "End Terminal": "10"}, {"Subscription Type": "Subscriber", "End Date": "1/5/2014 13:58", "Bike #": "557", "Zip Code": "94105", "Start Terminal": "56", "End Station": "Embarcadero at Bryant", "Start Station": "Beale at Market", "Duration": "1435", "Start Date": "1/5/2014 13:34", "Trip ID": "142952", "End Terminal": "54"}, {"Subscription Type": "Customer", "End Date": "1/5/2014 14:07", "Bike #": "97", "Zip Code": "94301", "Start Terminal": "32", "End Station": "Castro Street and El Camino Real", "Start Station": "Castro Street and El Camino Real", "Duration": "1689", "Start Date": "1/5/2014 13:39", "Trip ID": "142953", "End Terminal": "32"}, {"Subscription Type": "Customer", "End Date": "1/5/2014 14:07", "Bike #": "41", "Zip Code": "94301", "Start Terminal": "32", "End Station": "Castro Street and El Camino Real", "Start Station": "Castro Street and El Camino Real", "Duration": "1682", "Start Date": "1/5/2014 13:39", "Trip ID": "142954", "End Terminal": "32"}, {"Subscription Type": "Subscriber", "End Date": "1/5/2014 14:04", "Bike #": "534", "Zip Code": "95112", "Start Terminal": "70", "End Station": "San Francisco City Hall", "Start Station": "San Francisco Caltrain (Townsend at 4th)", "Duration": "1369", "Start Date": "1/5/2014 13:41", "Trip ID": "142955", "End Terminal": "58"}, {"Subscription Type": "Subscriber", "End Date": "1/5/2014 13:47", "Bike #": "197", "Zip Code": "94044", "Start Terminal": "16", "End Station": "SJSU 4th at San Carlos", "Start Station": "SJSU - San Salvador at 9th", "Duration": "336", "Start Date": "1/5/2014 13:41", "Trip ID": "142956", "End Terminal": "12"}, {"Subscription Type": "Subscriber", "End Date": "1/5/2014 13:47", "Bike #": "339", "Zip Code": "94043", "Start Terminal": "69", "End Station": "Townsend at 7th", "Start Station": "San Francisco Caltrain 2 (330 Townsend)", "Duration": "271", "Start Date": "1/5/2014 13:43", "Trip ID": "142957", "End Terminal": "65"}, {"Subscription Type": "Subscriber", "End Date": "1/5/2014 13:52", "Bike #": "555", "Zip Code": "94102", "Start Terminal": "67", "End Station": "Market at Sansome", "Start Station": "Market at 10th", "Duration": "487", "Start Date": "1/5/2014 13:44", "Trip ID": "142958", "End Terminal": "77"}, {"Subscription Type": "Subscriber", "End Date": "1/5/2014 13:53", "Bike #": "379", "Zip Code": "94103", "Start Terminal": "67", "End Station": "Powell Street BART", "Start Station": "Market at 10th", "Duration": "456", "Start Date": "1/5/2014 13:45", "Trip ID": "142959", "End Terminal": "53"}, {"Subscription Type": "Subscriber", "End Date": "1/5/2014 13:53", "Bike #": "326", "Zip Code": "94103", "Start Terminal": "67", "End Station": "Powell Street BART", "Start Station": "Market at 10th", "Duration": "468", "Start Date": "1/5/2014 13:45", "Trip ID": "142960", "End Terminal": "53"}, {"Subscription Type": "Customer", "End Date": "1/5/2014 18:27", "Bike #": "591", "Zip Code": "48356", "Start Terminal": "50", "End Station": "Grant Avenue at Columbus Avenue", "Start Station": "Harry Bridges Plaza (Ferry Building)", "Duration": "16890", "Start Date": "1/5/2014 13:45", "Trip ID": "142961", "End Terminal": "73"}, {"Subscription Type": "Customer", "End Date": "1/5/2014 18:27", "Bike #": "600", "Zip Code": "48356", "Start Terminal": "50", "End Station": "Grant Avenue at Columbus Avenue", "Start Station": "Harry Bridges Plaza (Ferry Building)", "Duration": "16905", "Start Date": "1/5/2014 13:45", "Trip ID": "142962", "End Terminal": "73"}, {"Subscription Type": "Subscriber", "End Date": "1/5/2014 14:03", "Bike #": "570", "Zip Code": "94941", "Start Terminal": "61", "End Station": "Harry Bridges Plaza (Ferry Building)", "Start Station": "2nd at Townsend", "Duration": "986", "Start Date": "1/5/2014 13:46", "Trip ID": "142963", "End Terminal": "50"}, {"Subscription Type": "Customer", "End Date": "1/5/2014 14:01", "Bike #": "60", "Zip Code": "8504", "Start Terminal": "4", "End Station": "San Jose Diridon Caltrain Station", "Start Station": "Santa Clara at Almaden", "Duration": "668", "Start Date": "1/5/2014 13:50", "Trip ID": "142964", "End Terminal": "2"}, {"Subscription Type": "Customer", "End Date": "1/5/2014 14:00", "Bike #": "109", "Zip Code": "8504", "Start Terminal": "4", "End Station": "San Jose Diridon Caltrain Station", "Start Station": "Santa Clara at Almaden", "Duration": "636", "Start Date": "1/5/2014 13:50", "Trip ID": "142965", "End Terminal": "2"}, {"Subscription Type": "Customer", "End Date": "1/5/2014 14:01", "Bike #": "142", "Zip Code": "8102", "Start Terminal": "4", "End Station": "San Jose Diridon Caltrain Station", "Start Station": "Santa Clara at Almaden", "Duration": "594", "Start Date": "1/5/2014 13:51", "Trip ID": "142966", "End Terminal": "2"}, {"Subscription Type": "Customer", "End Date": "1/5/2014 14:01", "Bike #": "211", "Zip Code": "8102", "Start Terminal": "4", "End Station": "San Jose Diridon Caltrain Station", "Start Station": "Santa Clara at Almaden", "Duration": "552", "Start Date": "1/5/2014 13:52", "Trip ID": "142967", "End Terminal": "2"}, {"Subscription Type": "Customer", "End Date": "1/5/2014 14:01", "Bike #": "202", "Zip Code": "8030", "Start Terminal": "4", "End Station": "San Jose Diridon Caltrain Station", "Start Station": "Santa Clara at Almaden", "Duration": "523", "Start Date": "1/5/2014 13:52", "Trip ID": "142968", "End Terminal": "2"}, {"Subscription Type": "Customer", "End Date": "1/5/2014 14:01", "Bike #": "145", "Zip Code": "8102", "Start Terminal": "4", "End Station": "San Jose Diridon Caltrain Station", "Start Station": "Santa Clara at Almaden", "Duration": "534", "Start Date": "1/5/2014 13:52", "Trip ID": "142969", "End Terminal": "2"}, {"Subscription Type": "Customer", "End Date": "1/5/2014 14:16", "Bike #": "317", "Zip Code": "94107", "Start Terminal": "48", "End Station": "Steuart at Market", "Start Station": "Embarcadero at Vallejo", "Duration": "1414", "Start Date": "1/5/2014 13:52", "Trip ID": "142970", "End Terminal": "74"}, {"Subscription Type": "Subscriber", "End Date": "1/5/2014 14:00", "Bike #": "310", "Zip Code": "95815", "Start Terminal": "53", "End Station": "Civic Center BART (7th at Market)", "Start Station": "Powell Street BART", "Duration": "234", "Start Date": "1/5/2014 13:56", "Trip ID": "142971", "End Terminal": "72"}, {"Subscription Type": "Subscriber", "End Date": "1/5/2014 13:59", "Bike #": "463", "Zip Code": "94103", "Start Terminal": "53", "End Station": "Civic Center BART (7th at Market)", "Start Station": "Powell Street BART", "Duration": "209", "Start Date": "1/5/2014 13:56", "Trip ID": "142972", "End Terminal": "72"}, {"Subscription Type": "Subscriber", "End Date": "1/5/2014 14:03", "Bike #": "437", "Zip Code": "94105", "Start Terminal": "68", "End Station": "Embarcadero at Folsom", "Start Station": "Yerba Buena Center of the Arts (3rd @ Howard)", "Duration": "565", "Start Date": "1/5/2014 13:54", "Trip ID": "142973", "End Terminal": "51"}, {"Subscription Type": "Subscriber", "End Date": "1/5/2014 13:58", "Bike #": "340", "Zip Code": "94105", "Start Terminal": "68", "End Station": "Yerba Buena Center of the Arts (3rd @ Howard)", "Start Station": "Yerba Buena Center of the Arts (3rd @ Howard)", "Duration": "226", "Start Date": "1/5/2014 13:54", "Trip ID": "142974", "End Terminal": "68"}, {"Subscription Type": "Customer", "End Date": "1/5/2014 14:50", "Bike #": "497", "Zip Code": "94601", "Start Terminal": "53", "End Station": "Powell Street BART", "Start Station": "Powell Street BART", "Duration": "3198", "Start Date": "1/5/2014 13:57", "Trip ID": "142975", "End Terminal": "53"}, {"Subscription Type": "Subscriber", "End Date": "1/5/2014 14:18", "Bike #": "557", "Zip Code": "94105", "Start Terminal": "54", "End Station": "Embarcadero at Bryant", "Start Station": "Embarcadero at Bryant", "Duration": "1206", "Start Date": "1/5/2014 13:58", "Trip ID": "142976", "End Terminal": "54"}, {"Subscription Type": "Customer", "End Date": "1/5/2014 14:50", "Bike #": "325", "Zip Code": "94601", "Start Terminal": "53", "End Station": "Powell Street BART", "Start Station": "Powell Street BART", "Duration": "3152", "Start Date": "1/5/2014 13:58", "Trip ID": "142977", "End Terminal": "53"}, {"Subscription Type": "Subscriber", "End Date": "1/5/2014 14:04", "Bike #": "409", "Zip Code": "94105", "Start Terminal": "68", "End Station": "Embarcadero at Folsom", "Start Station": "Yerba Buena Center of the Arts (3rd @ Howard)", "Duration": "332", "Start Date": "1/5/2014 13:59", "Trip ID": "142978", "End Terminal": "51"}, {"Subscription Type": "Subscriber", "End Date": "1/5/2014 14:06", "Bike #": "260", "Zip Code": "94107", "Start Terminal": "47", "End Station": "2nd at Townsend", "Start Station": "Post at Kearney", "Duration": "419", "Start Date": "1/5/2014 13:59", "Trip ID": "142979", "End Terminal": "61"}, {"Subscription Type": "Subscriber", "End Date": "1/5/2014 14:01", "Bike #": "509", "Zip Code": "94112", "Start Terminal": "55", "End Station": "Harry Bridges Plaza (Ferry Building)", "Start Station": "Temporary Transbay Terminal (Howard at Beale)", "Duration": "342", "Start Date": "1/5/2014 13:55", "Trip ID": "142980", "End Terminal": "50"}, {"Subscription Type": "Customer", "End Date": "1/5/2014 15:13", "Bike #": "145", "Zip Code": "8102", "Start Terminal": "2", "End Station": "San Jose Diridon Caltrain Station", "Start Station": "San Jose Diridon Caltrain Station", "Duration": "4144", "Start Date": "1/5/2014 14:04", "Trip ID": "142981", "End Terminal": "2"}, {"Subscription Type": "Customer", "End Date": "1/5/2014 15:13", "Bike #": "109", "Zip Code": "8504", "Start Terminal": "2", "End Station": "San Jose Diridon Caltrain Station", "Start Station": "San Jose Diridon Caltrain Station", "Duration": "4142", "Start Date": "1/5/2014 14:04", "Trip ID": "142982", "End Terminal": "2"}, {"Subscription Type": "Customer", "End Date": "1/5/2014 15:13", "Bike #": "60", "Zip Code": "8504", "Start Terminal": "2", "End Station": "San Jose Diridon Caltrain Station", "Start Station": "San Jose Diridon Caltrain Station", "Duration": "4121", "Start Date": "1/5/2014 14:04", "Trip ID": "142983", "End Terminal": "2"}, {"Subscription Type": "Customer", "End Date": "1/5/2014 15:12", "Bike #": "202", "Zip Code": "8030", "Start Terminal": "2", "End Station": "San Jose Diridon Caltrain Station", "Start Station": "San Jose Diridon Caltrain Station", "Duration": "4100", "Start Date": "1/5/2014 14:04", "Trip ID": "142984", "End Terminal": "2"}, {"Subscription Type": "Customer", "End Date": "1/5/2014 15:13", "Bike #": "211", "Zip Code": "8102", "Start Terminal": "2", "End Station": "San Jose Diridon Caltrain Station", "Start Station": "San Jose Diridon Caltrain Station", "Duration": "4106", "Start Date": "1/5/2014 14:04", "Trip ID": "142985", "End Terminal": "2"}, {"Subscription Type": "Customer", "End Date": "1/5/2014 14:16", "Bike #": "41", "Zip Code": "94301", "Start Terminal": "32", "End Station": "Mountain View Caltrain Station", "Start Station": "Castro Street and El Camino Real", "Duration": "493", "Start Date": "1/5/2014 14:08", "Trip ID": "142988", "End Terminal": "28"}, {"Subscription Type": "Customer", "End Date": "1/5/2014 14:16", "Bike #": "97", "Zip Code": "94301", "Start Terminal": "32", "End Station": "Mountain View Caltrain Station", "Start Station": "Castro Street and El Camino Real", "Duration": "493", "Start Date": "1/5/2014 14:08", "Trip ID": "142989", "End Terminal": "28"}, {"Subscription Type": "Customer", "End Date": "1/5/2014 14:28", "Bike #": "379", "Zip Code": "11104", "Start Terminal": "53", "End Station": "Embarcadero at Sansome", "Start Station": "Powell Street BART", "Duration": "1205", "Start Date": "1/5/2014 14:08", "Trip ID": "142990", "End Terminal": "60"}, {"Subscription Type": "Customer", "End Date": "1/5/2014 14:28", "Bike #": "492", "Zip Code": "11104", "Start Terminal": "53", "End Station": "Embarcadero at Sansome", "Start Station": "Powell Street BART", "Duration": "1183", "Start Date": "1/5/2014 14:08", "Trip ID": "142991", "End Terminal": "60"}, {"Subscription Type": "Subscriber", "End Date": "1/5/2014 14:17", "Bike #": "452", "Zip Code": "94108", "Start Terminal": "41", "End Station": "Yerba Buena Center of the Arts (3rd @ Howard)", "Start Station": "Clay at Battery", "Duration": "512", "Start Date": "1/5/2014 14:08", "Trip ID": "142992", "End Terminal": "68"}, {"Subscription Type": "Customer", "End Date": "1/5/2014 17:08", "Bike #": "551", "Zip Code": "64912", "Start Terminal": "41", "End Station": "Embarcadero at Sansome", "Start Station": "Clay at Battery", "Duration": "10645", "Start Date": "1/5/2014 14:11", "Trip ID": "142993", "End Terminal": "60"}, {"Subscription Type": "Subscriber", "End Date": "1/5/2014 14:28", "Bike #": "368", "Zip Code": "94158", "Start Terminal": "48", "End Station": "Market at 4th", "Start Station": "Embarcadero at Vallejo", "Duration": "745", "Start Date": "1/5/2014 14:15", "Trip ID": "142994", "End Terminal": "76"}, {"Subscription Type": "Customer", "End Date": "1/5/2014 14:31", "Bike #": "129", "Zip Code": "44074", "Start Terminal": "16", "End Station": "SJSU - San Salvador at 9th", "Start Station": "SJSU - San Salvador at 9th", "Duration": "948", "Start Date": "1/5/2014 14:16", "Trip ID": "142995", "End Terminal": "16"}, {"Subscription Type": "Subscriber", "End Date": "1/5/2014 14:30", "Bike #": "557", "Zip Code": "94105", "Start Terminal": "54", "End Station": "Embarcadero at Bryant", "Start Station": "Embarcadero at Bryant", "Duration": "729", "Start Date": "1/5/2014 14:18", "Trip ID": "142997", "End Terminal": "54"}, {"Subscription Type": "Customer", "End Date": "1/5/2014 14:35", "Bike #": "612", "Zip Code": "", "Start Terminal": "49", "End Station": "2nd at Townsend", "Start Station": "Spear at Folsom", "Duration": "836", "Start Date": "1/5/2014 14:21", "Trip ID": "142998", "End Terminal": "61"}, {"Subscription Type": "Subscriber", "End Date": "1/5/2014 14:31", "Bike #": "377", "Zip Code": "94538", "Start Terminal": "53", "End Station": "San Francisco Caltrain 2 (330 Townsend)", "Start Station": "Powell Street BART", "Duration": "468", "Start Date": "1/5/2014 14:23", "Trip ID": "142999", "End Terminal": "69"}, {"Subscription Type": "Subscriber", "End Date": "1/5/2014 14:34", "Bike #": "624", "Zip Code": "94105", "Start Terminal": "76", "End Station": "Howard at 2nd", "Start Station": "Market at 4th", "Duration": "539", "Start Date": "1/5/2014 14:25", "Trip ID": "143000", "End Terminal": "63"}, {"Subscription Type": "Subscriber", "End Date": "1/5/2014 14:38", "Bike #": "604", "Zip Code": "94105", "Start Terminal": "60", "End Station": "Spear at Folsom", "Start Station": "Embarcadero at Sansome", "Duration": "599", "Start Date": "1/5/2014 14:28", "Trip ID": "143001", "End Terminal": "49"}, {"Subscription Type": "Subscriber", "End Date": "1/5/2014 14:41", "Bike #": "354", "Zip Code": "94112", "Start Terminal": "46", "End Station": "Powell Street BART", "Start Station": "Washington at Kearney", "Duration": "699", "Start Date": "1/5/2014 14:30", "Trip ID": "143002", "End Terminal": "53"}, {"Subscription Type": "Subscriber", "End Date": "1/5/2014 15:02", "Bike #": "557", "Zip Code": "94105", "Start Terminal": "54", "End Station": "2nd at Townsend", "Start Station": "Embarcadero at Bryant", "Duration": "1930", "Start Date": "1/5/2014 14:30", "Trip ID": "143003", "End Terminal": "61"}, {"Subscription Type": "Customer", "End Date": "1/5/2014 16:32", "Bike #": "644", "Zip Code": "95032", "Start Terminal": "35", "End Station": "University and Emerson", "Start Station": "University and Emerson", "Duration": "7101", "Start Date": "1/5/2014 14:34", "Trip ID": "143005", "End Terminal": "35"}, {"Subscription Type": "Customer", "End Date": "1/5/2014 14:38", "Bike #": "178", "Zip Code": "95032", "Start Terminal": "35", "End Station": "University and Emerson", "Start Station": "University and Emerson", "Duration": "227", "Start Date": "1/5/2014 14:34", "Trip ID": "143006", "End Terminal": "35"}, {"Subscription Type": "Customer", "End Date": "1/5/2014 14:42", "Bike #": "505", "Zip Code": "94702", "Start Terminal": "47", "End Station": "Steuart at Market", "Start Station": "Post at Kearney", "Duration": "438", "Start Date": "1/5/2014 14:35", "Trip ID": "143007", "End Terminal": "74"}, {"Subscription Type": "Customer", "End Date": "1/5/2014 14:42", "Bike #": "328", "Zip Code": "94702", "Start Terminal": "47", "End Station": "Steuart at Market", "Start Station": "Post at Kearney", "Duration": "439", "Start Date": "1/5/2014 14:35", "Trip ID": "143008", "End Terminal": "74"}, {"Subscription Type": "Subscriber", "End Date": "1/5/2014 14:49", "Bike #": "550", "Zip Code": "94043", "Start Terminal": "61", "End Station": "Clay at Battery", "Start Station": "2nd at Townsend", "Duration": "839", "Start Date": "1/5/2014 14:35", "Trip ID": "143009", "End Terminal": "41"}, {"Subscription Type": "Subscriber", "End Date": "1/5/2014 14:40", "Bike #": "406", "Zip Code": "94105", "Start Terminal": "49", "End Station": "Howard at 2nd", "Start Station": "Spear at Folsom", "Duration": "302", "Start Date": "1/5/2014 14:35", "Trip ID": "143010", "End Terminal": "63"}, {"Subscription Type": "Subscriber", "End Date": "1/5/2014 14:44", "Bike #": "629", "Zip Code": "94109", "Start Terminal": "76", "End Station": "South Van Ness at Market", "Start Station": "Market at 4th", "Duration": "464", "Start Date": "1/5/2014 14:36", "Trip ID": "143011", "End Terminal": "66"}, {"Subscription Type": "Customer", "End Date": "1/5/2014 15:28", "Bike #": "418", "Zip Code": "", "Start Terminal": "50", "End Station": "Embarcadero at Sansome", "Start Station": "Harry Bridges Plaza (Ferry Building)", "Duration": "2772", "Start Date": "1/5/2014 14:42", "Trip ID": "143012", "End Terminal": "60"}, {"Subscription Type": "Customer", "End Date": "1/5/2014 15:29", "Bike #": "376", "Zip Code": "", "Start Terminal": "50", "End Station": "Embarcadero at Sansome", "Start Station": "Harry Bridges Plaza (Ferry Building)", "Duration": "2758", "Start Date": "1/5/2014 14:43", "Trip ID": "143013", "End Terminal": "60"}, {"Subscription Type": "Customer", "End Date": "1/5/2014 15:28", "Bike #": "491", "Zip Code": "", "Start Terminal": "50", "End Station": "Embarcadero at Sansome", "Start Station": "Harry Bridges Plaza (Ferry Building)", "Duration": "2736", "Start Date": "1/5/2014 14:43", "Trip ID": "143014", "End Terminal": "60"}, {"Subscription Type": "Customer", "End Date": "1/5/2014 15:28", "Bike #": "442", "Zip Code": "", "Start Terminal": "50", "End Station": "Embarcadero at Sansome", "Start Station": "Harry Bridges Plaza (Ferry Building)", "Duration": "2723", "Start Date": "1/5/2014 14:43", "Trip ID": "143015", "End Terminal": "60"}, {"Subscription Type": "Subscriber", "End Date": "1/5/2014 14:50", "Bike #": "431", "Zip Code": "94107", "Start Terminal": "64", "End Station": "San Francisco Caltrain 2 (330 Townsend)", "Start Station": "2nd at South Park", "Duration": "360", "Start Date": "1/5/2014 14:44", "Trip ID": "143016", "End Terminal": "69"}, {"Subscription Type": "Subscriber", "End Date": "1/5/2014 14:51", "Bike #": "450", "Zip Code": "94111", "Start Terminal": "51", "End Station": "Embarcadero at Sansome", "Start Station": "Embarcadero at Folsom", "Duration": "413", "Start Date": "1/5/2014 14:44", "Trip ID": "143017", "End Terminal": "60"}, {"Subscription Type": "Subscriber", "End Date": "1/5/2014 14:51", "Bike #": "375", "Zip Code": "94111", "Start Terminal": "51", "End Station": "Embarcadero at Sansome", "Start Station": "Embarcadero at Folsom", "Duration": "415", "Start Date": "1/5/2014 14:44", "Trip ID": "143018", "End Terminal": "60"}, {"Subscription Type": "Customer", "End Date": "1/5/2014 16:32", "Bike #": "261", "Zip Code": "95032", "Start Terminal": "35", "End Station": "University and Emerson", "Start Station": "University and Emerson", "Duration": "6471", "Start Date": "1/5/2014 14:44", "Trip ID": "143019", "End Terminal": "35"}, {"Subscription Type": "Subscriber", "End Date": "1/5/2014 15:04", "Bike #": "545", "Zip Code": "94103", "Start Terminal": "72", "End Station": "Market at Sansome", "Start Station": "Civic Center BART (7th at Market)", "Duration": "389", "Start Date": "1/5/2014 14:58", "Trip ID": "143020", "End Terminal": "77"}, {"Subscription Type": "Subscriber", "End Date": "1/5/2014 15:05", "Bike #": "605", "Zip Code": "94107", "Start Terminal": "77", "End Station": "2nd at Townsend", "Start Station": "Market at Sansome", "Duration": "381", "Start Date": "1/5/2014 14:59", "Trip ID": "143021", "End Terminal": "61"}, {"Subscription Type": "Customer", "End Date": "1/5/2014 16:53", "Bike #": "167", "Zip Code": "94306", "Start Terminal": "36", "End Station": "California Ave Caltrain Station", "Start Station": "California Ave Caltrain Station", "Duration": "6311", "Start Date": "1/5/2014 15:08", "Trip ID": "143022", "End Terminal": "36"}, {"Subscription Type": "Customer", "End Date": "1/5/2014 15:40", "Bike #": "441", "Zip Code": "94702", "Start Terminal": "50", "End Station": "Steuart at Market", "Start Station": "Harry Bridges Plaza (Ferry Building)", "Duration": "1865", "Start Date": "1/5/2014 15:09", "Trip ID": "143024", "End Terminal": "74"}, {"Subscription Type": "Customer", "End Date": "1/5/2014 15:40", "Bike #": "509", "Zip Code": "94702", "Start Terminal": "50", "End Station": "Steuart at Market", "Start Station": "Harry Bridges Plaza (Ferry Building)", "Duration": "1853", "Start Date": "1/5/2014 15:09", "Trip ID": "143025", "End Terminal": "74"}, {"Subscription Type": "Subscriber", "End Date": "1/5/2014 15:16", "Bike #": "504", "Zip Code": "94102", "Start Terminal": "59", "End Station": "Civic Center BART (7th at Market)", "Start Station": "Golden Gate at Polk", "Duration": "361", "Start Date": "1/5/2014 15:10", "Trip ID": "143027", "End Terminal": "72"}, {"Subscription Type": "Subscriber", "End Date": "1/5/2014 15:16", "Bike #": "345", "Zip Code": "94108", "Start Terminal": "59", "End Station": "Civic Center BART (7th at Market)", "Start Station": "Golden Gate at Polk", "Duration": "318", "Start Date": "1/5/2014 15:11", "Trip ID": "143028", "End Terminal": "72"}, {"Subscription Type": "Subscriber", "End Date": "1/5/2014 16:02", "Bike #": "484", "Zip Code": "94158", "Start Terminal": "70", "End Station": "Washington at Kearney", "Start Station": "San Francisco Caltrain (Townsend at 4th)", "Duration": "2742", "Start Date": "1/5/2014 15:17", "Trip ID": "143037", "End Terminal": "46"}, {"Subscription Type": "Customer", "End Date": "1/5/2014 15:26", "Bike #": "109", "Zip Code": "8504", "Start Terminal": "2", "End Station": "San Jose Civic Center", "Start Station": "San Jose Diridon Caltrain Station", "Duration": "566", "Start Date": "1/5/2014 15:16", "Trip ID": "143038", "End Terminal": "3"}, {"Subscription Type": "Customer", "End Date": "1/5/2014 15:26", "Bike #": "211", "Zip Code": "8102", "Start Terminal": "2", "End Station": "San Jose Civic Center", "Start Station": "San Jose Diridon Caltrain Station", "Duration": "551", "Start Date": "1/5/2014 15:17", "Trip ID": "143039", "End Terminal": "3"}, {"Subscription Type": "Customer", "End Date": "1/5/2014 15:26", "Bike #": "142", "Zip Code": "8102", "Start Terminal": "2", "End Station": "San Jose Civic Center", "Start Station": "San Jose Diridon Caltrain Station", "Duration": "542", "Start Date": "1/5/2014 15:17", "Trip ID": "143040", "End Terminal": "3"}, {"Subscription Type": "Customer", "End Date": "1/5/2014 15:26", "Bike #": "60", "Zip Code": "8504", "Start Terminal": "2", "End Station": "San Jose Civic Center", "Start Station": "San Jose Diridon Caltrain Station", "Duration": "585", "Start Date": "1/5/2014 15:17", "Trip ID": "143041", "End Terminal": "3"}, {"Subscription Type": "Customer", "End Date": "1/5/2014 15:26", "Bike #": "202", "Zip Code": "8030", "Start Terminal": "2", "End Station": "San Jose Civic Center", "Start Station": "San Jose Diridon Caltrain Station", "Duration": "522", "Start Date": "1/5/2014 15:17", "Trip ID": "143042", "End Terminal": "3"}, {"Subscription Type": "Subscriber", "End Date": "1/5/2014 15:34", "Bike #": "439", "Zip Code": "94107", "Start Terminal": "62", "End Station": "5th at Howard", "Start Station": "2nd at Folsom", "Duration": "839", "Start Date": "1/5/2014 15:20", "Trip ID": "143043", "End Terminal": "57"}, {"Subscription Type": "Customer", "End Date": "1/5/2014 15:36", "Bike #": "317", "Zip Code": "94107", "Start Terminal": "74", "End Station": "2nd at Folsom", "Start Station": "Steuart at Market", "Duration": "940", "Start Date": "1/5/2014 15:20", "Trip ID": "143044", "End Terminal": "62"}, {"Subscription Type": "Subscriber", "End Date": "1/5/2014 15:39", "Bike #": "341", "Zip Code": "94107", "Start Terminal": "61", "End Station": "Embarcadero at Vallejo", "Start Station": "2nd at Townsend", "Duration": "1074", "Start Date": "1/5/2014 15:22", "Trip ID": "143045", "End Terminal": "48"}, {"Subscription Type": "Subscriber", "End Date": "1/5/2014 15:39", "Bike #": "557", "Zip Code": "94107", "Start Terminal": "61", "End Station": "Embarcadero at Vallejo", "Start Station": "2nd at Townsend", "Duration": "1063", "Start Date": "1/5/2014 15:22", "Trip ID": "143046", "End Terminal": "48"}, {"Subscription Type": "Subscriber", "End Date": "1/5/2014 15:46", "Bike #": "345", "Zip Code": "94108", "Start Terminal": "72", "End Station": "Washington at Kearney", "Start Station": "Civic Center BART (7th at Market)", "Duration": "1038", "Start Date": "1/5/2014 15:29", "Trip ID": "143048", "End Terminal": "46"}, {"Subscription Type": "Subscriber", "End Date": "1/5/2014 15:40", "Bike #": "555", "Zip Code": "94102", "Start Terminal": "77", "End Station": "San Francisco City Hall", "Start Station": "Market at Sansome", "Duration": "693", "Start Date": "1/5/2014 15:29", "Trip ID": "143049", "End Terminal": "58"}, {"Subscription Type": "Subscriber", "End Date": "1/5/2014 15:46", "Bike #": "504", "Zip Code": "94102", "Start Terminal": "72", "End Station": "Washington at Kearney", "Start Station": "Civic Center BART (7th at Market)", "Duration": "1003", "Start Date": "1/5/2014 15:29", "Trip ID": "143050", "End Terminal": "46"}, {"Subscription Type": "Customer", "End Date": "1/5/2014 15:37", "Bike #": "399", "Zip Code": "", "Start Terminal": "61", "End Station": "Spear at Folsom", "Start Station": "2nd at Townsend", "Duration": "483", "Start Date": "1/5/2014 15:29", "Trip ID": "143051", "End Terminal": "49"}, {"Subscription Type": "Subscriber", "End Date": "1/5/2014 15:42", "Bike #": "424", "Zip Code": "94107", "Start Terminal": "68", "End Station": "Townsend at 7th", "Start Station": "Yerba Buena Center of the Arts (3rd @ Howard)", "Duration": "612", "Start Date": "1/5/2014 15:31", "Trip ID": "143052", "End Terminal": "65"}, {"Subscription Type": "Subscriber", "End Date": "1/5/2014 15:43", "Bike #": "522", "Zip Code": "94105", "Start Terminal": "74", "End Station": "Spear at Folsom", "Start Station": "Steuart at Market", "Duration": "192", "Start Date": "1/5/2014 15:40", "Trip ID": "143056", "End Terminal": "49"}, {"Subscription Type": "Subscriber", "End Date": "1/5/2014 15:56", "Bike #": "577", "Zip Code": "95815", "Start Terminal": "53", "End Station": "San Francisco Caltrain 2 (330 Townsend)", "Start Station": "Powell Street BART", "Duration": "583", "Start Date": "1/5/2014 15:46", "Trip ID": "143057", "End Terminal": "69"}, {"Subscription Type": "Subscriber", "End Date": "1/5/2014 16:04", "Bike #": "401", "Zip Code": "94107", "Start Terminal": "68", "End Station": "Embarcadero at Bryant", "Start Station": "Yerba Buena Center of the Arts (3rd @ Howard)", "Duration": "664", "Start Date": "1/5/2014 15:53", "Trip ID": "143058", "End Terminal": "54"}, {"Subscription Type": "Subscriber", "End Date": "1/5/2014 16:10", "Bike #": "545", "Zip Code": "94103", "Start Terminal": "77", "End Station": "Market at Sansome", "Start Station": "Market at Sansome", "Duration": "965", "Start Date": "1/5/2014 15:54", "Trip ID": "143059", "End Terminal": "77"}, {"Subscription Type": "Subscriber", "End Date": "1/5/2014 16:02", "Bike #": "406", "Zip Code": "94105", "Start Terminal": "63", "End Station": "Spear at Folsom", "Start Station": "Howard at 2nd", "Duration": "312", "Start Date": "1/5/2014 15:57", "Trip ID": "143060", "End Terminal": "49"}, {"Subscription Type": "Subscriber", "End Date": "1/5/2014 16:18", "Bike #": "516", "Zip Code": "94102", "Start Terminal": "66", "End Station": "2nd at Townsend", "Start Station": "South Van Ness at Market", "Duration": "1192", "Start Date": "1/5/2014 15:58", "Trip ID": "143061", "End Terminal": "61"}, {"Subscription Type": "Customer", "End Date": "1/5/2014 16:47", "Bike #": "630", "Zip Code": "94103", "Start Terminal": "66", "End Station": "South Van Ness at Market", "Start Station": "South Van Ness at Market", "Duration": "2722", "Start Date": "1/5/2014 16:02", "Trip ID": "143062", "End Terminal": "66"}, {"Subscription Type": "Subscriber", "End Date": "1/5/2014 16:24", "Bike #": "585", "Zip Code": "94114", "Start Terminal": "48", "End Station": "Harry Bridges Plaza (Ferry Building)", "Start Station": "Embarcadero at Vallejo", "Duration": "509", "Start Date": "1/5/2014 16:16", "Trip ID": "143071", "End Terminal": "50"}, {"Subscription Type": "Subscriber", "End Date": "1/5/2014 16:26", "Bike #": "494", "Zip Code": "94941", "Start Terminal": "74", "End Station": "Embarcadero at Bryant", "Start Station": "Steuart at Market", "Duration": "357", "Start Date": "1/5/2014 16:20", "Trip ID": "143072", "End Terminal": "54"}, {"Subscription Type": "Subscriber", "End Date": "1/5/2014 16:26", "Bike #": "161", "Zip Code": "94040", "Start Terminal": "28", "End Station": "Mountain View Caltrain Station", "Start Station": "Mountain View Caltrain Station", "Duration": "135", "Start Date": "1/5/2014 16:23", "Trip ID": "143075", "End Terminal": "28"}, {"Subscription Type": "Subscriber", "End Date": "1/5/2014 16:39", "Bike #": "97", "Zip Code": "94040", "Start Terminal": "28", "End Station": "San Antonio Caltrain Station", "Start Station": "Mountain View Caltrain Station", "Duration": "745", "Start Date": "1/5/2014 16:26", "Trip ID": "143076", "End Terminal": "29"}, {"Subscription Type": "Subscriber", "End Date": "1/5/2014 16:45", "Bike #": "516", "Zip Code": "94102", "Start Terminal": "61", "End Station": "San Francisco Caltrain 2 (330 Townsend)", "Start Station": "2nd at Townsend", "Duration": "279", "Start Date": "1/5/2014 16:41", "Trip ID": "143077", "End Terminal": "69"}, {"Subscription Type": "Subscriber", "End Date": "1/5/2014 16:58", "Bike #": "550", "Zip Code": "94043", "Start Terminal": "41", "End Station": "San Francisco Caltrain 2 (330 Townsend)", "Start Station": "Clay at Battery", "Duration": "886", "Start Date": "1/5/2014 16:43", "Trip ID": "143078", "End Terminal": "69"}, {"Subscription Type": "Customer", "End Date": "1/5/2014 16:59", "Bike #": "563", "Zip Code": "94133", "Start Terminal": "61", "End Station": "Grant Avenue at Columbus Avenue", "Start Station": "2nd at Townsend", "Duration": "745", "Start Date": "1/5/2014 16:47", "Trip ID": "143079", "End Terminal": "73"}, {"Subscription Type": "Subscriber", "End Date": "1/5/2014 16:57", "Bike #": "207", "Zip Code": "95113", "Start Terminal": "10", "End Station": "San Pedro Square", "Start Station": "San Jose City Hall", "Duration": "555", "Start Date": "1/5/2014 16:47", "Trip ID": "143082", "End Terminal": "6"}, {"Subscription Type": "Customer", "End Date": "1/5/2014 17:06", "Bike #": "354", "Zip Code": "11104", "Start Terminal": "53", "End Station": "Embarcadero at Bryant", "Start Station": "Powell Street BART", "Duration": "864", "Start Date": "1/5/2014 16:52", "Trip ID": "143084", "End Terminal": "54"}, {"Subscription Type": "Customer", "End Date": "1/5/2014 17:06", "Bike #": "325", "Zip Code": "11104", "Start Terminal": "53", "End Station": "Embarcadero at Bryant", "Start Station": "Powell Street BART", "Duration": "862", "Start Date": "1/5/2014 16:52", "Trip ID": "143085", "End Terminal": "54"}, {"Subscription Type": "Subscriber", "End Date": "1/5/2014 17:04", "Bike #": "556", "Zip Code": "94107", "Start Terminal": "64", "End Station": "Market at Sansome", "Start Station": "2nd at South Park", "Duration": "416", "Start Date": "1/5/2014 16:58", "Trip ID": "143086", "End Terminal": "77"}, {"Subscription Type": "Subscriber", "End Date": "1/5/2014 17:15", "Bike #": "442", "Zip Code": "94107", "Start Terminal": "60", "End Station": "2nd at Townsend", "Start Station": "Embarcadero at Sansome", "Duration": "896", "Start Date": "1/5/2014 17:00", "Trip ID": "143087", "End Terminal": "61"}, {"Subscription Type": "Subscriber", "End Date": "1/5/2014 17:14", "Bike #": "375", "Zip Code": "94107", "Start Terminal": "60", "End Station": "2nd at Townsend", "Start Station": "Embarcadero at Sansome", "Duration": "881", "Start Date": "1/5/2014 17:00", "Trip ID": "143088", "End Terminal": "61"}, {"Subscription Type": "Customer", "End Date": "1/5/2014 17:26", "Bike #": "491", "Zip Code": "94080", "Start Terminal": "60", "End Station": "Embarcadero at Bryant", "Start Station": "Embarcadero at Sansome", "Duration": "1198", "Start Date": "1/5/2014 17:06", "Trip ID": "143090", "End Terminal": "54"}, {"Subscription Type": "Subscriber", "End Date": "1/5/2014 17:17", "Bike #": "260", "Zip Code": "94115", "Start Terminal": "61", "End Station": "Mechanics Plaza (Market at Battery)", "Start Station": "2nd at Townsend", "Duration": "486", "Start Date": "1/5/2014 17:09", "Trip ID": "143091", "End Terminal": "75"}, {"Subscription Type": "Customer", "End Date": "1/6/2014 9:32", "Bike #": "679", "Zip Code": "94041", "Start Terminal": "27", "End Station": "Mountain View Caltrain Station", "Start Station": "Mountain View City Hall", "Duration": "59026", "Start Date": "1/5/2014 17:08", "Trip ID": "143092", "End Terminal": "28"}, {"Subscription Type": "Subscriber", "End Date": "1/5/2014 17:13", "Bike #": "437", "Zip Code": "94105", "Start Terminal": "51", "End Station": "Embarcadero at Bryant", "Start Station": "Embarcadero at Folsom", "Duration": "169", "Start Date": "1/5/2014 17:11", "Trip ID": "143093", "End Terminal": "54"}, {"Subscription Type": "Subscriber", "End Date": "1/5/2014 17:33", "Bike #": "605", "Zip Code": "94107", "Start Terminal": "61", "End Station": "Harry Bridges Plaza (Ferry Building)", "Start Station": "2nd at Townsend", "Duration": "336", "Start Date": "1/5/2014 17:28", "Trip ID": "143114", "End Terminal": "50"}, {"Subscription Type": "Subscriber", "End Date": "1/5/2014 17:39", "Bike #": "527", "Zip Code": "94117", "Start Terminal": "76", "End Station": "Howard at 2nd", "Start Station": "Market at 4th", "Duration": "313", "Start Date": "1/5/2014 17:33", "Trip ID": "143115", "End Terminal": "63"}, {"Subscription Type": "Subscriber", "End Date": "1/5/2014 17:42", "Bike #": "288", "Zip Code": "94109", "Start Terminal": "58", "End Station": "San Francisco City Hall", "Start Station": "San Francisco City Hall", "Duration": "474", "Start Date": "1/5/2014 17:34", "Trip ID": "143116", "End Terminal": "58"}, {"Subscription Type": "Subscriber", "End Date": "1/5/2014 17:44", "Bike #": "489", "Zip Code": "94110", "Start Terminal": "66", "End Station": "Market at 4th", "Start Station": "South Van Ness at Market", "Duration": "596", "Start Date": "1/5/2014 17:34", "Trip ID": "143117", "End Terminal": "76"}, {"Subscription Type": "Customer", "End Date": "1/5/2014 17:41", "Bike #": "485", "Zip Code": "10024", "Start Terminal": "62", "End Station": "2nd at Townsend", "Start Station": "2nd at Folsom", "Duration": "257", "Start Date": "1/5/2014 17:37", "Trip ID": "143118", "End Terminal": "61"}, {"Subscription Type": "Customer", "End Date": "1/5/2014 17:57", "Bike #": "491", "Zip Code": "94111", "Start Terminal": "54", "End Station": "Embarcadero at Sansome", "Start Station": "Embarcadero at Bryant", "Duration": "1218", "Start Date": "1/5/2014 17:37", "Trip ID": "143119", "End Terminal": "60"}, {"Subscription Type": "Customer", "End Date": "1/5/2014 17:57", "Bike #": "325", "Zip Code": "94111", "Start Terminal": "54", "End Station": "Embarcadero at Sansome", "Start Station": "Embarcadero at Bryant", "Duration": "1139", "Start Date": "1/5/2014 17:38", "Trip ID": "143120", "End Terminal": "60"}, {"Subscription Type": "Subscriber", "End Date": "1/5/2014 17:53", "Bike #": "551", "Zip Code": "95139", "Start Terminal": "60", "End Station": "Embarcadero at Bryant", "Start Station": "Embarcadero at Sansome", "Duration": "823", "Start Date": "1/5/2014 17:39", "Trip ID": "143121", "End Terminal": "54"}, {"Subscription Type": "Subscriber", "End Date": "1/5/2014 17:53", "Bike #": "376", "Zip Code": "94105", "Start Terminal": "60", "End Station": "Embarcadero at Bryant", "Start Station": "Embarcadero at Sansome", "Duration": "817", "Start Date": "1/5/2014 17:39", "Trip ID": "143122", "End Terminal": "54"}, {"Subscription Type": "Customer", "End Date": "1/5/2014 17:43", "Bike #": "425", "Zip Code": "94103", "Start Terminal": "66", "End Station": "South Van Ness at Market", "Start Station": "South Van Ness at Market", "Duration": "204", "Start Date": "1/5/2014 17:40", "Trip ID": "143123", "End Terminal": "66"}, {"Subscription Type": "Subscriber", "End Date": "1/5/2014 17:57", "Bike #": "369", "Zip Code": "94102", "Start Terminal": "53", "End Station": "Embarcadero at Vallejo", "Start Station": "Powell Street BART", "Duration": "605", "Start Date": "1/5/2014 17:47", "Trip ID": "143124", "End Terminal": "48"}, {"Subscription Type": "Subscriber", "End Date": "1/5/2014 17:54", "Bike #": "580", "Zip Code": "94542", "Start Terminal": "73", "End Station": "Steuart at Market", "Start Station": "Grant Avenue at Columbus Avenue", "Duration": "363", "Start Date": "1/5/2014 17:48", "Trip ID": "143125", "End Terminal": "74"}, {"Subscription Type": "Subscriber", "End Date": "1/5/2014 17:54", "Bike #": "425", "Zip Code": "94102", "Start Terminal": "66", "End Station": "Powell Street BART", "Start Station": "South Van Ness at Market", "Duration": "378", "Start Date": "1/5/2014 17:48", "Trip ID": "143126", "End Terminal": "53"}, {"Subscription Type": "Subscriber", "End Date": "1/5/2014 17:54", "Bike #": "569", "Zip Code": "94105", "Start Terminal": "73", "End Station": "Steuart at Market", "Start Station": "Grant Avenue at Columbus Avenue", "Duration": "350", "Start Date": "1/5/2014 17:48", "Trip ID": "143127", "End Terminal": "74"}, {"Subscription Type": "Subscriber", "End Date": "1/5/2014 18:00", "Bike #": "322", "Zip Code": "94117", "Start Terminal": "66", "End Station": "Townsend at 7th", "Start Station": "South Van Ness at Market", "Duration": "503", "Start Date": "1/5/2014 17:52", "Trip ID": "143128", "End Terminal": "65"}, {"Subscription Type": "Subscriber", "End Date": "1/5/2014 17:57", "Bike #": "400", "Zip Code": "94109", "Start Terminal": "66", "End Station": "Golden Gate at Polk", "Start Station": "South Van Ness at Market", "Duration": "304", "Start Date": "1/5/2014 17:52", "Trip ID": "143130", "End Terminal": "59"}, {"Subscription Type": "Subscriber", "End Date": "1/5/2014 17:59", "Bike #": "545", "Zip Code": "94103", "Start Terminal": "77", "End Station": "Civic Center BART (7th at Market)", "Start Station": "Market at Sansome", "Duration": "383", "Start Date": "1/5/2014 17:53", "Trip ID": "143131", "End Terminal": "72"}, {"Subscription Type": "Subscriber", "End Date": "1/5/2014 18:05", "Bike #": "353", "Zip Code": "94103", "Start Terminal": "77", "End Station": "South Van Ness at Market", "Start Station": "Market at Sansome", "Duration": "714", "Start Date": "1/5/2014 17:53", "Trip ID": "143132", "End Terminal": "66"}, {"Subscription Type": "Subscriber", "End Date": "1/5/2014 18:06", "Bike #": "377", "Zip Code": "94158", "Start Terminal": "53", "End Station": "San Francisco Caltrain (Townsend at 4th)", "Start Station": "Powell Street BART", "Duration": "469", "Start Date": "1/5/2014 17:58", "Trip ID": "143133", "End Terminal": "70"}, {"Subscription Type": "Subscriber", "End Date": "1/5/2014 18:22", "Bike #": "445", "Zip Code": "94158", "Start Terminal": "74", "End Station": "San Francisco Caltrain (Townsend at 4th)", "Start Station": "Steuart at Market", "Duration": "524", "Start Date": "1/5/2014 18:13", "Trip ID": "143134", "End Terminal": "70"}, {"Subscription Type": "Subscriber", "End Date": "1/5/2014 18:28", "Bike #": "555", "Zip Code": "94117", "Start Terminal": "58", "End Station": "2nd at Townsend", "Start Station": "San Francisco City Hall", "Duration": "779", "Start Date": "1/5/2014 18:15", "Trip ID": "143135", "End Terminal": "61"}, {"Subscription Type": "Customer", "End Date": "1/5/2014 18:24", "Bike #": "361", "Zip Code": "64081", "Start Terminal": "76", "End Station": "Clay at Battery", "Start Station": "Market at 4th", "Duration": "522", "Start Date": "1/5/2014 18:15", "Trip ID": "143136", "End Terminal": "41"}, {"Subscription Type": "Subscriber", "End Date": "1/5/2014 18:27", "Bike #": "413", "Zip Code": "94118", "Start Terminal": "73", "End Station": "Commercial at Montgomery", "Start Station": "Grant Avenue at Columbus Avenue", "Duration": "204", "Start Date": "1/5/2014 18:23", "Trip ID": "143140", "End Terminal": "45"}, {"Subscription Type": "Subscriber", "End Date": "1/5/2014 18:45", "Bike #": "530", "Zip Code": "94590", "Start Terminal": "68", "End Station": "Harry Bridges Plaza (Ferry Building)", "Start Station": "Yerba Buena Center of the Arts (3rd @ Howard)", "Duration": "620", "Start Date": "1/5/2014 18:35", "Trip ID": "143146", "End Terminal": "50"}, {"Subscription Type": "Subscriber", "End Date": "1/5/2014 19:00", "Bike #": "425", "Zip Code": "94103", "Start Terminal": "53", "End Station": "Beale at Market", "Start Station": "Powell Street BART", "Duration": "404", "Start Date": "1/5/2014 18:53", "Trip ID": "143150", "End Terminal": "56"}, {"Subscription Type": "Subscriber", "End Date": "1/6/2014 0:51", "Bike #": "563", "Zip Code": "94133", "Start Terminal": "73", "End Station": "Grant Avenue at Columbus Avenue", "Start Station": "Grant Avenue at Columbus Avenue", "Duration": "20649", "Start Date": "1/5/2014 19:07", "Trip ID": "143153", "End Terminal": "73"}, {"Subscription Type": "Subscriber", "End Date": "1/5/2014 19:18", "Bike #": "452", "Zip Code": "94158", "Start Terminal": "68", "End Station": "San Francisco Caltrain (Townsend at 4th)", "Start Station": "Yerba Buena Center of the Arts (3rd @ Howard)", "Duration": "413", "Start Date": "1/5/2014 19:11", "Trip ID": "143154", "End Terminal": "70"}, {"Subscription Type": "Subscriber", "End Date": "1/5/2014 19:22", "Bike #": "511", "Zip Code": "94103", "Start Terminal": "76", "End Station": "Market at 10th", "Start Station": "Market at 4th", "Duration": "641", "Start Date": "1/5/2014 19:12", "Trip ID": "143155", "End Terminal": "67"}, {"Subscription Type": "Subscriber", "End Date": "1/5/2014 19:22", "Bike #": "468", "Zip Code": "94103", "Start Terminal": "76", "End Station": "Market at 10th", "Start Station": "Market at 4th", "Duration": "610", "Start Date": "1/5/2014 19:12", "Trip ID": "143156", "End Terminal": "67"}, {"Subscription Type": "Subscriber", "End Date": "1/5/2014 19:20", "Bike #": "528", "Zip Code": "94102", "Start Terminal": "75", "End Station": "Market at 4th", "Start Station": "Mechanics Plaza (Market at Battery)", "Duration": "273", "Start Date": "1/5/2014 19:16", "Trip ID": "143157", "End Terminal": "76"}, {"Subscription Type": "Subscriber", "End Date": "1/5/2014 19:26", "Bike #": "425", "Zip Code": "94103", "Start Terminal": "56", "End Station": "Market at 4th", "Start Station": "Beale at Market", "Duration": "365", "Start Date": "1/5/2014 19:20", "Trip ID": "143158", "End Terminal": "76"}, {"Subscription Type": "Subscriber", "End Date": "1/5/2014 19:28", "Bike #": "438", "Zip Code": "94105", "Start Terminal": "51", "End Station": "Embarcadero at Bryant", "Start Station": "Embarcadero at Folsom", "Duration": "225", "Start Date": "1/5/2014 19:24", "Trip ID": "143159", "End Terminal": "54"}, {"Subscription Type": "Subscriber", "End Date": "1/5/2014 19:50", "Bike #": "402", "Zip Code": "94102", "Start Terminal": "42", "End Station": "Powell Street BART", "Start Station": "Davis at Jackson", "Duration": "1096", "Start Date": "1/5/2014 19:32", "Trip ID": "143161", "End Terminal": "53"}, {"Subscription Type": "Subscriber", "End Date": "1/5/2014 19:50", "Bike #": "405", "Zip Code": "94133", "Start Terminal": "55", "End Station": "Embarcadero at Sansome", "Start Station": "Temporary Transbay Terminal (Howard at Beale)", "Duration": "505", "Start Date": "1/5/2014 19:42", "Trip ID": "143162", "End Terminal": "60"}, {"Subscription Type": "Subscriber", "End Date": "1/5/2014 19:58", "Bike #": "506", "Zip Code": "94133", "Start Terminal": "49", "End Station": "Washington at Kearney", "Start Station": "Spear at Folsom", "Duration": "761", "Start Date": "1/5/2014 19:46", "Trip ID": "143163", "End Terminal": "46"}, {"Subscription Type": "Subscriber", "End Date": "1/5/2014 20:15", "Bike #": "551", "Zip Code": "94158", "Start Terminal": "60", "End Station": "Yerba Buena Center of the Arts (3rd @ Howard)", "Start Station": "Embarcadero at Sansome", "Duration": "1204", "Start Date": "1/5/2014 19:55", "Trip ID": "143164", "End Terminal": "68"}, {"Subscription Type": "Subscriber", "End Date": "1/5/2014 20:03", "Bike #": "233", "Zip Code": "94301", "Start Terminal": "27", "End Station": "Mountain View Caltrain Station", "Start Station": "Mountain View City Hall", "Duration": "280", "Start Date": "1/5/2014 19:59", "Trip ID": "143165", "End Terminal": "28"}, {"Subscription Type": "Subscriber", "End Date": "1/5/2014 20:12", "Bike #": "380", "Zip Code": "94102", "Start Terminal": "42", "End Station": "Washington at Kearney", "Start Station": "Davis at Jackson", "Duration": "482", "Start Date": "1/5/2014 20:04", "Trip ID": "143168", "End Terminal": "46"}, {"Subscription Type": "Subscriber", "End Date": "1/5/2014 20:12", "Bike #": "352", "Zip Code": "94108", "Start Terminal": "42", "End Station": "Washington at Kearney", "Start Station": "Davis at Jackson", "Duration": "477", "Start Date": "1/5/2014 20:04", "Trip ID": "143169", "End Terminal": "46"}, {"Subscription Type": "Customer", "End Date": "1/5/2014 20:42", "Bike #": "519", "Zip Code": "94702", "Start Terminal": "51", "End Station": "Market at 4th", "Start Station": "Embarcadero at Folsom", "Duration": "1256", "Start Date": "1/5/2014 20:22", "Trip ID": "143177", "End Terminal": "76"}, {"Subscription Type": "Customer", "End Date": "1/5/2014 22:00", "Bike #": "314", "Zip Code": "94702", "Start Terminal": "51", "End Station": "Market at 4th", "Start Station": "Embarcadero at Folsom", "Duration": "5807", "Start Date": "1/5/2014 20:23", "Trip ID": "143178", "End Terminal": "76"}, {"Subscription Type": "Subscriber", "End Date": "1/5/2014 21:02", "Bike #": "531", "Zip Code": "94103", "Start Terminal": "57", "End Station": "San Francisco Caltrain (Townsend at 4th)", "Start Station": "5th at Howard", "Duration": "311", "Start Date": "1/5/2014 20:57", "Trip ID": "143184", "End Terminal": "70"}, {"Subscription Type": "Subscriber", "End Date": "1/5/2014 21:11", "Bike #": "149", "Zip Code": "95112", "Start Terminal": "2", "End Station": "Japantown", "Start Station": "San Jose Diridon Caltrain Station", "Duration": "851", "Start Date": "1/5/2014 20:57", "Trip ID": "143185", "End Terminal": "9"}, {"Subscription Type": "Subscriber", "End Date": "1/5/2014 21:13", "Bike #": "513", "Zip Code": "94103", "Start Terminal": "70", "End Station": "Steuart at Market", "Start Station": "San Francisco Caltrain (Townsend at 4th)", "Duration": "663", "Start Date": "1/5/2014 21:02", "Trip ID": "143186", "End Terminal": "74"}, {"Subscription Type": "Subscriber", "End Date": "1/5/2014 21:19", "Bike #": "502", "Zip Code": "94107", "Start Terminal": "64", "End Station": "5th at Howard", "Start Station": "2nd at South Park", "Duration": "482", "Start Date": "1/5/2014 21:11", "Trip ID": "143187", "End Terminal": "57"}, {"Subscription Type": "Subscriber", "End Date": "1/5/2014 21:19", "Bike #": "417", "Zip Code": "94107", "Start Terminal": "64", "End Station": "5th at Howard", "Start Station": "2nd at South Park", "Duration": "459", "Start Date": "1/5/2014 21:11", "Trip ID": "143188", "End Terminal": "57"}, {"Subscription Type": "Subscriber", "End Date": "1/5/2014 21:18", "Bike #": "509", "Zip Code": "94103", "Start Terminal": "74", "End Station": "Davis at Jackson", "Start Station": "Steuart at Market", "Duration": "265", "Start Date": "1/5/2014 21:14", "Trip ID": "143189", "End Terminal": "42"}, {"Subscription Type": "Subscriber", "End Date": "1/5/2014 21:18", "Bike #": "290", "Zip Code": "94105", "Start Terminal": "51", "End Station": "Embarcadero at Bryant", "Start Station": "Embarcadero at Folsom", "Duration": "146", "Start Date": "1/5/2014 21:16", "Trip ID": "143190", "End Terminal": "54"}, {"Subscription Type": "Subscriber", "End Date": "1/5/2014 21:28", "Bike #": "347", "Zip Code": "94103", "Start Terminal": "42", "End Station": "5th at Howard", "Start Station": "Davis at Jackson", "Duration": "571", "Start Date": "1/5/2014 21:18", "Trip ID": "143191", "End Terminal": "57"}, {"Subscription Type": "Subscriber", "End Date": "1/5/2014 21:44", "Bike #": "427", "Zip Code": "94107", "Start Terminal": "61", "End Station": "Civic Center BART (7th at Market)", "Start Station": "2nd at Townsend", "Duration": "635", "Start Date": "1/5/2014 21:33", "Trip ID": "143192", "End Terminal": "72"}, {"Subscription Type": "Subscriber", "End Date": "1/5/2014 22:42", "Bike #": "561", "Zip Code": "94102", "Start Terminal": "53", "End Station": "Grant Avenue at Columbus Avenue", "Start Station": "Powell Street BART", "Duration": "530", "Start Date": "1/5/2014 22:33", "Trip ID": "143193", "End Terminal": "73"}, {"Subscription Type": "Subscriber", "End Date": "1/5/2014 22:38", "Bike #": "302", "Zip Code": "94301", "Start Terminal": "28", "End Station": "Mountain View City Hall", "Start Station": "Mountain View Caltrain Station", "Duration": "265", "Start Date": "1/5/2014 22:34", "Trip ID": "143194", "End Terminal": "27"}, {"Subscription Type": "Subscriber", "End Date": "1/5/2014 23:31", "Bike #": "398", "Zip Code": "94105", "Start Terminal": "61", "End Station": "Spear at Folsom", "Start Station": "2nd at Townsend", "Duration": "278", "Start Date": "1/5/2014 23:26", "Trip ID": "143195", "End Terminal": "49"}, {"Subscription Type": "Subscriber", "End Date": "1/5/2014 23:42", "Bike #": "413", "Zip Code": "94102", "Start Terminal": "45", "End Station": "Market at 4th", "Start Station": "Commercial at Montgomery", "Duration": "302", "Start Date": "1/5/2014 23:37", "Trip ID": "143196", "End Terminal": "76"}, {"Subscription Type": "Subscriber", "End Date": "1/5/2014 23:56", "Bike #": "481", "Zip Code": "94102", "Start Terminal": "60", "End Station": "Civic Center BART (7th at Market)", "Start Station": "Embarcadero at Sansome", "Duration": "972", "Start Date": "1/5/2014 23:40", "Trip ID": "143197", "End Terminal": "72"}, {"Subscription Type": "Subscriber", "End Date": "1/5/2014 23:46", "Bike #": "554", "Zip Code": "94107", "Start Terminal": "57", "End Station": "Howard at 2nd", "Start Station": "5th at Howard", "Duration": "335", "Start Date": "1/5/2014 23:40", "Trip ID": "143198", "End Terminal": "63"}]